<data datetime="12/18/2016 00:00:00">
  <TRAFFICXML description="Station=VTV6 (channel=VTV6) ">
    <row>
      <EXTERSTRID>N1_201278</EXTERSTRID>
      <DURATION>1575</DURATION>
      <COD_PROGRA>DH.V6.HOMNAY.00H-12H</COD_PROGRA>
      <SERIES_ID>
      </SERIES_ID>
      <SERIES_NAME>
      </SERIES_NAME>
      <EPISODE>
      </EPISODE>
      <SEASON>
      </SEASON>
      <DESCRIZIO>Trôi - hôm nay - 0h - 12h00 (Ngày HH: 31/12/2016)</DESCRIZIO>
      <TITLE>Trôi - hôm nay - 0h - 12h00 (Ngày HH: 31/12/2016)</TITLE>
      <ASPECT>H</ASPECT>
      <TIMECODE_I>0</TIMECODE_I>
      <TIMECODE_O>1574</TIMECODE_O>
      <DATA>18/12/2016</DATA>
      <ORA>1500</ORA>
      <NEWTYPE>CDQB</NEWTYPE>
      <TENCM>Nhận diện kênh</TENCM>
      <MADVSX>
      </MADVSX>
      <TENDVSX>
      </TENDVSX>
      <NGUOISX>
      </NGUOISX>
      <DTNGUOISX>
      </DTNGUOISX>
      <GHICHU>
      </GHICHU>
      <PRODUCTION_NOTE>
      </PRODUCTION_NOTE>
      <Editor_Name>
      </Editor_Name>
      <TRANGTHAI>1</TRANGTHAI>
      <NGUOITH>
      </NGUOITH>
      <NGAYTH>
      </NGAYTH>
      <HTPS>0</HTPS>
      <LUU>
      </LUU>
      <KIEU>1</KIEU>
      <DOHOA>
      </DOHOA>
      <KENHPS>VTV6</KENHPS>
      <DUYET>1</DUYET>
      <LUUTULIEU>True</LUUTULIEU>
      <NGUONTULIEU>True</NGUONTULIEU>
      <QC>True</QC>
      <DATA_SCAD>07/01/2017</DATA_SCAD>
      <SOLANQC>0</SOLANQC>
      <TenCongBo>
      </TenCongBo>
      <TenChuyenMucCongbo>
      </TenChuyenMucCongbo>
    </row>
    <row>
      <EXTERSTRID>T0_c93397f6-0e80-4ade-8815-bc48f27d3c9b</EXTERSTRID>
      <DURATION>67575</DURATION>
      <COD_PROGRA>KTPPT_TINHYEUNGAYTHANG_TAP19</COD_PROGRA>
      <SERIES_ID>
      </SERIES_ID>
      <SERIES_NAME>
      </SERIES_NAME>
      <EPISODE>
      </EPISODE>
      <SEASON>
      </SEASON>
      <DESCRIZIO>Phim truyện NN: Tình yêu ngay thẳng - Tập 19</DESCRIZIO>
      <TITLE>Phim truyện NN: Tình yêu ngay thẳng - Tập 19</TITLE>
      <ASPECT>H</ASPECT>
      <TIMECODE_I>0</TIMECODE_I>
      <TIMECODE_O>67574</TIMECODE_O>
      <DATA>18/12/2016</DATA>
      <DATA_SCAD>18/12/2017</DATA_SCAD>
      <ORA>90000</ORA>
      <NEWTYPE>PT</NEWTYPE>
      <TENCM>Phim truyện NN</TENCM>
      <NGUOISX>
      </NGUOISX>
      <DTNGUOISX>
      </DTNGUOISX>
      <GHICHU>
      </GHICHU>
      <PRODUCTION_NOTE>
      </PRODUCTION_NOTE>
      <Editor_Name>
      </Editor_Name>
      <TRANGTHAI>1</TRANGTHAI>
      <NGUOITH>
      </NGUOITH>
      <NGAYTH>
      </NGAYTH>
      <HTPS>1</HTPS>
      <LUU>
      </LUU>
      <KIEU>0</KIEU>
      <CRAWL_DESC>[Aspect Conversion] Code=4 [MediaSet]</CRAWL_DESC>
      <NOTES>
      </NOTES>
      <DOHOA>
      </DOHOA>
      <MADVSX>49</MADVSX>
      <TENDVSX>
      </TENDVSX>
      <KENHPS>VTV6</KENHPS>
      <KENHPSHT>VTV6</KENHPSHT>
      <DUYET>1</DUYET>
      <LUUTULIEU>true</LUUTULIEU>
      <NGUONTULIEU>0</NGUONTULIEU>
      <QC>True</QC>
      <SOLANQC>0</SOLANQC>
      <TenCongBo>Tình yêu ngay thẳng - Tập 19</TenCongBo>
      <TenChuyenMucCongbo>Phim truyện</TenChuyenMucCongbo>
    </row>
    <row>
      <EXTERSTRID>T0_90df0bce-e81c-4f23-91cb-220ea3d4130d</EXTERSTRID>
      <DURATION>41775</DURATION>
      <COD_PROGRA>TTNNC_CONDUONGTOIDI</COD_PROGRA>
      <SERIES_ID>
      </SERIES_ID>
      <SERIES_NAME>
      </SERIES_NAME>
      <EPISODE>
      </EPISODE>
      <SEASON>
      </SEASON>
      <DESCRIZIO>Ngược chiều: Con đường tôi đi</DESCRIZIO>
      <TITLE>Ngược chiều: Con đường tôi đi</TITLE>
      <ASPECT>H</ASPECT>
      <TIMECODE_I>0</TIMECODE_I>
      <TIMECODE_O>41774</TIMECODE_O>
      <DATA>18/12/2016</DATA>
      <DATA_SCAD>16/06/2017</DATA_SCAD>
      <ORA>157500</ORA>
      <NEWTYPE>NC</NEWTYPE>
      <TENCM>Ngược chiều</TENCM>
      <NGUOISX>
      </NGUOISX>
      <DTNGUOISX>
      </DTNGUOISX>
      <GHICHU>
      </GHICHU>
      <PRODUCTION_NOTE>
      </PRODUCTION_NOTE>
      <Editor_Name>
      </Editor_Name>
      <TRANGTHAI>1</TRANGTHAI>
      <NGUOITH>
      </NGUOITH>
      <NGAYTH>
      </NGAYTH>
      <HTPS>1</HTPS>
      <LUU>
      </LUU>
      <KIEU>0</KIEU>
      <CRAWL_DESC>[Aspect Conversion] Code=4 [MediaSet]</CRAWL_DESC>
      <NOTES>
      </NOTES>
      <DOHOA>
      </DOHOA>
      <MADVSX>87</MADVSX>
      <TENDVSX>
      </TENDVSX>
      <KENHPS>VTV6</KENHPS>
      <KENHPSHT>VTV6</KENHPSHT>
      <DUYET>1</DUYET>
      <LUUTULIEU>true</LUUTULIEU>
      <NGUONTULIEU>0</NGUONTULIEU>
      <QC>True</QC>
      <SOLANQC>0</SOLANQC>
      <TenCongBo>Con đường tôi đi</TenCongBo>
      <TenChuyenMucCongbo>Ngược chiều</TenChuyenMucCongbo>
    </row>
    <row>
      <EXTERSTRID>T0_17ccb62d-11bd-4c76-9411-232b629f3c95</EXTERSTRID>
      <DURATION>72600</DURATION>
      <COD_PROGRA>KGKPTG_CHUYENDICUNGUYHIEM_P1</COD_PROGRA>
      <SERIES_ID>
      </SERIES_ID>
      <SERIES_NAME>
      </SERIES_NAME>
      <EPISODE>
      </EPISODE>
      <SEASON>
      </SEASON>
      <DESCRIZIO>Khám phá thế giới: Những chuyến di cư nguy hiểm - P1" Cuộc di cư vĩ đại của Ngựa vằn"</DESCRIZIO>
      <TITLE>Khám phá thế giới: Những chuyến di cư nguy hiểm - P1" Cuộc di cư vĩ đại của Ngựa vằn"</TITLE>
      <ASPECT>H</ASPECT>
      <TIMECODE_I>0</TIMECODE_I>
      <TIMECODE_O>72599</TIMECODE_O>
      <DATA>18/12/2016</DATA>
      <DATA_SCAD>16/12/2026</DATA_SCAD>
      <ORA>202500</ORA>
      <NEWTYPE>KPTG</NEWTYPE>
      <TENCM>Khám phá thế giới</TENCM>
      <NGUOISX>Nguyễn Phương Thảo</NGUOISX>
      <DTNGUOISX>
      </DTNGUOISX>
      <GHICHU>
      </GHICHU>
      <PRODUCTION_NOTE>
      </PRODUCTION_NOTE>
      <Editor_Name>
      </Editor_Name>
      <TRANGTHAI>1</TRANGTHAI>
      <NGUOITH>
      </NGUOITH>
      <NGAYTH>
      </NGAYTH>
      <HTPS>1</HTPS>
      <LUU>
      </LUU>
      <KIEU>0</KIEU>
      <CRAWL_DESC>[Aspect Conversion] Code=4 [MediaSet]</CRAWL_DESC>
      <NOTES>
      </NOTES>
      <DOHOA>
      </DOHOA>
      <MADVSX>59</MADVSX>
      <TENDVSX>
      </TENDVSX>
      <KENHPS>VTV6</KENHPS>
      <KENHPSHT>VTV6</KENHPSHT>
      <DUYET>1</DUYET>
      <LUUTULIEU>true</LUUTULIEU>
      <NGUONTULIEU>0</NGUONTULIEU>
      <QC>True</QC>
      <SOLANQC>0</SOLANQC>
      <TenCongBo>Những chuyến di cư nguy hiểm - Phần 1</TenCongBo>
      <TenChuyenMucCongbo>Khám phá thế giới</TenChuyenMucCongbo>
    </row>
    <row>
      <EXTERSTRID>T01_55993317-5f66-4d01-a10d-e8149e8a8a73</EXTERSTRID>
      <DURATION>540</DURATION>
      <COD_PROGRA>VFCBOOI_BOOIMINHDIDAUTHE_1712</COD_PROGRA>
      <SERIES_ID>
      </SERIES_ID>
      <SERIES_NAME>
      </SERIES_NAME>
      <EPISODE>
      </EPISODE>
      <SEASON>
      </SEASON>
      <DESCRIZIO>Bố ơi! Mình đi đâu thế (V6): Bố ơi mình đi đâu thế - Tập 33 - 17/12_1</DESCRIZIO>
      <TITLE>Bố ơi! Mình đi đâu thế (V6): Bố ơi mình đi đâu thế - Tập 33 - 17/12_1</TITLE>
      <ASPECT>H</ASPECT>
      <TIMECODE_I>0</TIMECODE_I>
      <TIMECODE_O>13499</TIMECODE_O>
      <DATA>18/12/2016</DATA>
      <DATA_SCAD>20/03/2017</DATA_SCAD>
      <ORA>270000</ORA>
      <NEWTYPE>BOOI</NEWTYPE>
      <TENCM>Bố ơi! Mình đi đâu thế (V6)</TENCM>
      <NGUOISX>
      </NGUOISX>
      <DTNGUOISX>
      </DTNGUOISX>
      <GHICHU>
      </GHICHU>
      <PRODUCTION_NOTE>
      </PRODUCTION_NOTE>
      <Editor_Name>
      </Editor_Name>
      <TRANGTHAI>1</TRANGTHAI>
      <NGUOITH>
      </NGUOITH>
      <NGAYTH>
      </NGAYTH>
      <HTPS>1</HTPS>
      <LUU>
      </LUU>
      <KIEU>0</KIEU>
      <CRAWL_DESC>[Aspect Conversion] Code=4 [MediaSet]</CRAWL_DESC>
      <NOTES>
      </NOTES>
      <DOHOA>
      </DOHOA>
      <MADVSX>
      </MADVSX>
      <TENDVSX>
      </TENDVSX>
      <KENHPS>VTV6</KENHPS>
      <KENHPSHT>VTV6</KENHPSHT>
      <DUYET>1</DUYET>
      <LUUTULIEU>true</LUUTULIEU>
      <NGUONTULIEU>0</NGUONTULIEU>
      <QC>True</QC>
      <SOLANQC>0</SOLANQC>
      <TenCongBo>
      </TenCongBo>
      <TenChuyenMucCongbo>Bố ơi! Mình đi đâu thế?</TenChuyenMucCongbo>
    </row>
    <row>
      <EXTERSTRID>T02_55993317-5f66-4d01-a10d-e8149e8a8a73</EXTERSTRID>
      <DURATION>540</DURATION>
      <COD_PROGRA>VFCBOOI_BOOIMINHDIDAUTHE_1712_2</COD_PROGRA>
      <SERIES_ID>
      </SERIES_ID>
      <SERIES_NAME>
      </SERIES_NAME>
      <EPISODE>
      </EPISODE>
      <SEASON>
      </SEASON>
      <DESCRIZIO>Bố ơi! Mình đi đâu thế (V6): Bố ơi mình đi đâu thế - Tập 33 - 17/12_2</DESCRIZIO>
      <TITLE>Bố ơi! Mình đi đâu thế (V6): Bố ơi mình đi đâu thế - Tập 33 - 17/12_2</TITLE>
      <ASPECT>H</ASPECT>
      <TIMECODE_I>0</TIMECODE_I>
      <TIMECODE_O>13499</TIMECODE_O>
      <DATA>18/12/2016</DATA>
      <DATA_SCAD>20/03/2017</DATA_SCAD>
      <ORA>270540</ORA>
      <NEWTYPE>BOOI</NEWTYPE>
      <TENCM>Bố ơi! Mình đi đâu thế (V6)</TENCM>
      <NGUOISX>
      </NGUOISX>
      <DTNGUOISX>
      </DTNGUOISX>
      <GHICHU>
      </GHICHU>
      <PRODUCTION_NOTE>
      </PRODUCTION_NOTE>
      <Editor_Name>
      </Editor_Name>
      <TRANGTHAI>1</TRANGTHAI>
      <NGUOITH>
      </NGUOITH>
      <NGAYTH>
      </NGAYTH>
      <HTPS>1</HTPS>
      <LUU>
      </LUU>
      <KIEU>0</KIEU>
      <CRAWL_DESC>[Aspect Conversion] Code=4 [MediaSet]</CRAWL_DESC>
      <NOTES>
      </NOTES>
      <DOHOA>
      </DOHOA>
      <MADVSX>
      </MADVSX>
      <TENDVSX>
      </TENDVSX>
      <KENHPS>VTV6</KENHPS>
      <KENHPSHT>VTV6</KENHPSHT>
      <DUYET>1</DUYET>
      <LUUTULIEU>true</LUUTULIEU>
      <NGUONTULIEU>0</NGUONTULIEU>
      <QC>True</QC>
      <SOLANQC>0</SOLANQC>
      <TenCongBo>
      </TenCongBo>
      <TenChuyenMucCongbo>Bố ơi! Mình đi đâu thế?</TenChuyenMucCongbo>
    </row>
    <row>
      <EXTERSTRID>T03_55993317-5f66-4d01-a10d-e8149e8a8a73</EXTERSTRID>
      <DURATION>540</DURATION>
      <COD_PROGRA>VFCBOOI_BOOIMINHDIDAUTHE_1712_3</COD_PROGRA>
      <SERIES_ID>
      </SERIES_ID>
      <SERIES_NAME>
      </SERIES_NAME>
      <EPISODE>
      </EPISODE>
      <SEASON>
      </SEASON>
      <DESCRIZIO>Bố ơi! Mình đi đâu thế (V6): Bố ơi mình đi đâu thế - Tập 33 - 17/12_3</DESCRIZIO>
      <TITLE>Bố ơi! Mình đi đâu thế (V6): Bố ơi mình đi đâu thế - Tập 33 - 17/12_3</TITLE>
      <ASPECT>H</ASPECT>
      <TIMECODE_I>0</TIMECODE_I>
      <TIMECODE_O>13499</TIMECODE_O>
      <DATA>18/12/2016</DATA>
      <DATA_SCAD>20/03/2017</DATA_SCAD>
      <ORA>271080</ORA>
      <NEWTYPE>BOOI</NEWTYPE>
      <TENCM>Bố ơi! Mình đi đâu thế (V6)</TENCM>
      <NGUOISX>
      </NGUOISX>
      <DTNGUOISX>
      </DTNGUOISX>
      <GHICHU>
      </GHICHU>
      <PRODUCTION_NOTE>
      </PRODUCTION_NOTE>
      <Editor_Name>
      </Editor_Name>
      <TRANGTHAI>1</TRANGTHAI>
      <NGUOITH>
      </NGUOITH>
      <NGAYTH>
      </NGAYTH>
      <HTPS>1</HTPS>
      <LUU>
      </LUU>
      <KIEU>0</KIEU>
      <CRAWL_DESC>[Aspect Conversion] Code=4 [MediaSet]</CRAWL_DESC>
      <NOTES>
      </NOTES>
      <DOHOA>
      </DOHOA>
      <MADVSX>
      </MADVSX>
      <TENDVSX>
      </TENDVSX>
      <KENHPS>VTV6</KENHPS>
      <KENHPSHT>VTV6</KENHPSHT>
      <DUYET>1</DUYET>
      <LUUTULIEU>true</LUUTULIEU>
      <NGUONTULIEU>0</NGUONTULIEU>
      <QC>True</QC>
      <SOLANQC>0</SOLANQC>
      <TenCongBo>
      </TenCongBo>
      <TenChuyenMucCongbo>Bố ơi! Mình đi đâu thế?</TenChuyenMucCongbo>
    </row>
    <row>
      <EXTERSTRID>T04_55993317-5f66-4d01-a10d-e8149e8a8a73</EXTERSTRID>
      <DURATION>540</DURATION>
      <COD_PROGRA>VFCBOOI_BOOIMINHDIDAUTHE_1712_4</COD_PROGRA>
      <SERIES_ID>
      </SERIES_ID>
      <SERIES_NAME>
      </SERIES_NAME>
      <EPISODE>
      </EPISODE>
      <SEASON>
      </SEASON>
      <DESCRIZIO>Bố ơi! Mình đi đâu thế (V6): Bố ơi mình đi đâu thế - Tập 33 - 17/12_4</DESCRIZIO>
      <TITLE>Bố ơi! Mình đi đâu thế (V6): Bố ơi mình đi đâu thế - Tập 33 - 17/12_4</TITLE>
      <ASPECT>H</ASPECT>
      <TIMECODE_I>0</TIMECODE_I>
      <TIMECODE_O>13499</TIMECODE_O>
      <DATA>18/12/2016</DATA>
      <DATA_SCAD>20/03/2017</DATA_SCAD>
      <ORA>271620</ORA>
      <NEWTYPE>BOOI</NEWTYPE>
      <TENCM>Bố ơi! Mình đi đâu thế (V6)</TENCM>
      <NGUOISX>
      </NGUOISX>
      <DTNGUOISX>
      </DTNGUOISX>
      <GHICHU>
      </GHICHU>
      <PRODUCTION_NOTE>
      </PRODUCTION_NOTE>
      <Editor_Name>
      </Editor_Name>
      <TRANGTHAI>1</TRANGTHAI>
      <NGUOITH>
      </NGUOITH>
      <NGAYTH>
      </NGAYTH>
      <HTPS>1</HTPS>
      <LUU>
      </LUU>
      <KIEU>0</KIEU>
      <CRAWL_DESC>[Aspect Conversion] Code=4 [MediaSet]</CRAWL_DESC>
      <NOTES>
      </NOTES>
      <DOHOA>
      </DOHOA>
      <MADVSX>
      </MADVSX>
      <TENDVSX>
      </TENDVSX>
      <KENHPS>VTV6</KENHPS>
      <KENHPSHT>VTV6</KENHPSHT>
      <DUYET>1</DUYET>
      <LUUTULIEU>true</LUUTULIEU>
      <NGUONTULIEU>0</NGUONTULIEU>
      <QC>True</QC>
      <SOLANQC>0</SOLANQC>
      <TenCongBo>
      </TenCongBo>
      <TenChuyenMucCongbo>Bố ơi! Mình đi đâu thế?</TenChuyenMucCongbo>
    </row>
    <row>
      <EXTERSTRID>T05_55993317-5f66-4d01-a10d-e8149e8a8a73</EXTERSTRID>
      <DURATION>540</DURATION>
      <COD_PROGRA>VFCBOOI_BOOIMINHDIDAUTHE_1712_5</COD_PROGRA>
      <SERIES_ID>
      </SERIES_ID>
      <SERIES_NAME>
      </SERIES_NAME>
      <EPISODE>
      </EPISODE>
      <SEASON>
      </SEASON>
      <DESCRIZIO>Bố ơi! Mình đi đâu thế (V6): Bố ơi mình đi đâu thế - Tập 33 - 17/12_5</DESCRIZIO>
      <TITLE>Bố ơi! Mình đi đâu thế (V6): Bố ơi mình đi đâu thế - Tập 33 - 17/12_5</TITLE>
      <ASPECT>H</ASPECT>
      <TIMECODE_I>0</TIMECODE_I>
      <TIMECODE_O>13499</TIMECODE_O>
      <DATA>18/12/2016</DATA>
      <DATA_SCAD>20/03/2017</DATA_SCAD>
      <ORA>272160</ORA>
      <NEWTYPE>BOOI</NEWTYPE>
      <TENCM>Bố ơi! Mình đi đâu thế (V6)</TENCM>
      <NGUOISX>
      </NGUOISX>
      <DTNGUOISX>
      </DTNGUOISX>
      <GHICHU>
      </GHICHU>
      <PRODUCTION_NOTE>
      </PRODUCTION_NOTE>
      <Editor_Name>
      </Editor_Name>
      <TRANGTHAI>1</TRANGTHAI>
      <NGUOITH>
      </NGUOITH>
      <NGAYTH>
      </NGAYTH>
      <HTPS>1</HTPS>
      <LUU>
      </LUU>
      <KIEU>0</KIEU>
      <CRAWL_DESC>[Aspect Conversion] Code=4 [MediaSet]</CRAWL_DESC>
      <NOTES>
      </NOTES>
      <DOHOA>
      </DOHOA>
      <MADVSX>
      </MADVSX>
      <TENDVSX>
      </TENDVSX>
      <KENHPS>VTV6</KENHPS>
      <KENHPSHT>VTV6</KENHPSHT>
      <DUYET>1</DUYET>
      <LUUTULIEU>true</LUUTULIEU>
      <NGUONTULIEU>0</NGUONTULIEU>
      <QC>True</QC>
      <SOLANQC>0</SOLANQC>
      <TenCongBo>
      </TenCongBo>
      <TenChuyenMucCongbo>Bố ơi! Mình đi đâu thế?</TenChuyenMucCongbo>
    </row>
    <row>
      <EXTERSTRID>T0_6662f683-3910-472b-8112-c2321e21aa25</EXTERSTRID>
      <DURATION>41850</DURATION>
      <COD_PROGRA>TTNHNAD_SO58</COD_PROGRA>
      <SERIES_ID>
      </SERIES_ID>
      <SERIES_NAME>
      </SERIES_NAME>
      <EPISODE>
      </EPISODE>
      <SEASON>
      </SEASON>
      <DESCRIZIO>Hôm nay ai đến?: Số 58</DESCRIZIO>
      <TITLE>Hôm nay ai đến?: Số 58</TITLE>
      <ASPECT>H</ASPECT>
      <TIMECODE_I>0</TIMECODE_I>
      <TIMECODE_O>41849</TIMECODE_O>
      <DATA>18/12/2016</DATA>
      <DATA_SCAD>18/12/2017</DATA_SCAD>
      <ORA>360000</ORA>
      <NEWTYPE>HNAD</NEWTYPE>
      <TENCM>Hôm nay ai đến?</TENCM>
      <NGUOISX>
      </NGUOISX>
      <DTNGUOISX>
      </DTNGUOISX>
      <GHICHU>
      </GHICHU>
      <PRODUCTION_NOTE>
      </PRODUCTION_NOTE>
      <Editor_Name>
      </Editor_Name>
      <TRANGTHAI>1</TRANGTHAI>
      <NGUOITH>
      </NGUOITH>
      <NGAYTH>
      </NGAYTH>
      <HTPS>1</HTPS>
      <LUU>
      </LUU>
      <KIEU>0</KIEU>
      <CRAWL_DESC>[Aspect Conversion] Code=4 [MediaSet]</CRAWL_DESC>
      <NOTES>
      </NOTES>
      <DOHOA>
      </DOHOA>
      <MADVSX>87</MADVSX>
      <TENDVSX>
      </TENDVSX>
      <KENHPS>VTV6</KENHPS>
      <KENHPSHT>VTV6</KENHPSHT>
      <DUYET>1</DUYET>
      <LUUTULIEU>true</LUUTULIEU>
      <NGUONTULIEU>0</NGUONTULIEU>
      <QC>True</QC>
      <SOLANQC>0</SOLANQC>
      <TenCongBo>
      </TenCongBo>
      <TenChuyenMucCongbo>Hôm nay ai đến?</TenChuyenMucCongbo>
    </row>
    <row>
      <EXTERSTRID>T01_cc5db5b6-29f0-4c01-b69e-a765ca2ff6af</EXTERSTRID>
      <DURATION>750</DURATION>
      <COD_PROGRA>BHDBDPC_SO53_2016</COD_PROGRA>
      <SERIES_ID>
      </SERIES_ID>
      <SERIES_NAME>
      </SERIES_NAME>
      <EPISODE>
      </EPISODE>
      <SEASON>
      </SEASON>
      <DESCRIZIO>Biệt đội phong cách: Số 53 - 2016 (2 lần Pop up, 4 lần Logo xoay - Không chạy khi phát lại)_1</DESCRIZIO>
      <TITLE>Biệt đội phong cách: Số 53 - 2016 (2 lần Pop up, 4 lần Logo xoay - Không chạy khi phát lại)_1</TITLE>
      <ASPECT>H</ASPECT>
      <TIMECODE_I>0</TIMECODE_I>
      <TIMECODE_O>18749</TIMECODE_O>
      <DATA>18/12/2016</DATA>
      <DATA_SCAD>18/12/2017</DATA_SCAD>
      <ORA>405000</ORA>
      <NEWTYPE>BDPC</NEWTYPE>
      <TENCM>Biệt đội phong cách</TENCM>
      <NGUOISX>
      </NGUOISX>
      <DTNGUOISX>
      </DTNGUOISX>
      <GHICHU>
      </GHICHU>
      <PRODUCTION_NOTE>
      </PRODUCTION_NOTE>
      <Editor_Name>
      </Editor_Name>
      <TRANGTHAI>1</TRANGTHAI>
      <NGUOITH>
      </NGUOITH>
      <NGAYTH>
      </NGAYTH>
      <HTPS>1</HTPS>
      <LUU>
      </LUU>
      <KIEU>0</KIEU>
      <CRAWL_DESC>[Aspect Conversion] Code=4 [MediaSet]</CRAWL_DESC>
      <NOTES>
      </NOTES>
      <DOHOA>
      </DOHOA>
      <MADVSX>
      </MADVSX>
      <TENDVSX>
      </TENDVSX>
      <KENHPS>VTV6</KENHPS>
      <KENHPSHT>VTV6</KENHPSHT>
      <DUYET>0</DUYET>
      <LUUTULIEU>true</LUUTULIEU>
      <NGUONTULIEU>0</NGUONTULIEU>
      <QC>True</QC>
      <SOLANQC>0</SOLANQC>
      <TenCongBo>
      </TenCongBo>
      <TenChuyenMucCongbo>Biệt đội phong cách</TenChuyenMucCongbo>
    </row>
    <row>
      <EXTERSTRID>T02_cc5db5b6-29f0-4c01-b69e-a765ca2ff6af</EXTERSTRID>
      <DURATION>750</DURATION>
      <COD_PROGRA>BHDBDPC_SO53_2016_2</COD_PROGRA>
      <SERIES_ID>
      </SERIES_ID>
      <SERIES_NAME>
      </SERIES_NAME>
      <EPISODE>
      </EPISODE>
      <SEASON>
      </SEASON>
      <DESCRIZIO>Biệt đội phong cách: Số 53 - 2016 (2 lần Pop up, 4 lần Logo xoay - Không chạy khi phát lại)_2</DESCRIZIO>
      <TITLE>Biệt đội phong cách: Số 53 - 2016 (2 lần Pop up, 4 lần Logo xoay - Không chạy khi phát lại)_2</TITLE>
      <ASPECT>H</ASPECT>
      <TIMECODE_I>0</TIMECODE_I>
      <TIMECODE_O>18749</TIMECODE_O>
      <DATA>18/12/2016</DATA>
      <DATA_SCAD>18/12/2017</DATA_SCAD>
      <ORA>405750</ORA>
      <NEWTYPE>BDPC</NEWTYPE>
      <TENCM>Biệt đội phong cách</TENCM>
      <NGUOISX>
      </NGUOISX>
      <DTNGUOISX>
      </DTNGUOISX>
      <GHICHU>
      </GHICHU>
      <PRODUCTION_NOTE>
      </PRODUCTION_NOTE>
      <Editor_Name>
      </Editor_Name>
      <TRANGTHAI>1</TRANGTHAI>
      <NGUOITH>
      </NGUOITH>
      <NGAYTH>
      </NGAYTH>
      <HTPS>1</HTPS>
      <LUU>
      </LUU>
      <KIEU>0</KIEU>
      <CRAWL_DESC>[Aspect Conversion] Code=4 [MediaSet]</CRAWL_DESC>
      <NOTES>
      </NOTES>
      <DOHOA>
      </DOHOA>
      <MADVSX>
      </MADVSX>
      <TENDVSX>
      </TENDVSX>
      <KENHPS>VTV6</KENHPS>
      <KENHPSHT>VTV6</KENHPSHT>
      <DUYET>0</DUYET>
      <LUUTULIEU>true</LUUTULIEU>
      <NGUONTULIEU>0</NGUONTULIEU>
      <QC>True</QC>
      <SOLANQC>0</SOLANQC>
      <TenCongBo>
      </TenCongBo>
      <TenChuyenMucCongbo>Biệt đội phong cách</TenChuyenMucCongbo>
    </row>
    <row>
      <EXTERSTRID>T03_cc5db5b6-29f0-4c01-b69e-a765ca2ff6af</EXTERSTRID>
      <DURATION>750</DURATION>
      <COD_PROGRA>BHDBDPC_SO53_2016_3</COD_PROGRA>
      <SERIES_ID>
      </SERIES_ID>
      <SERIES_NAME>
      </SERIES_NAME>
      <EPISODE>
      </EPISODE>
      <SEASON>
      </SEASON>
      <DESCRIZIO>Biệt đội phong cách: Số 53 - 2016 (2 lần Pop up, 4 lần Logo xoay - Không chạy khi phát lại)_3</DESCRIZIO>
      <TITLE>Biệt đội phong cách: Số 53 - 2016 (2 lần Pop up, 4 lần Logo xoay - Không chạy khi phát lại)_3</TITLE>
      <ASPECT>H</ASPECT>
      <TIMECODE_I>0</TIMECODE_I>
      <TIMECODE_O>18749</TIMECODE_O>
      <DATA>18/12/2016</DATA>
      <DATA_SCAD>18/12/2017</DATA_SCAD>
      <ORA>406500</ORA>
      <NEWTYPE>BDPC</NEWTYPE>
      <TENCM>Biệt đội phong cách</TENCM>
      <NGUOISX>
      </NGUOISX>
      <DTNGUOISX>
      </DTNGUOISX>
      <GHICHU>
      </GHICHU>
      <PRODUCTION_NOTE>
      </PRODUCTION_NOTE>
      <Editor_Name>
      </Editor_Name>
      <TRANGTHAI>1</TRANGTHAI>
      <NGUOITH>
      </NGUOITH>
      <NGAYTH>
      </NGAYTH>
      <HTPS>1</HTPS>
      <LUU>
      </LUU>
      <KIEU>0</KIEU>
      <CRAWL_DESC>[Aspect Conversion] Code=4 [MediaSet]</CRAWL_DESC>
      <NOTES>
      </NOTES>
      <DOHOA>
      </DOHOA>
      <MADVSX>
      </MADVSX>
      <TENDVSX>
      </TENDVSX>
      <KENHPS>VTV6</KENHPS>
      <KENHPSHT>VTV6</KENHPSHT>
      <DUYET>0</DUYET>
      <LUUTULIEU>true</LUUTULIEU>
      <NGUONTULIEU>0</NGUONTULIEU>
      <QC>True</QC>
      <SOLANQC>0</SOLANQC>
      <TenCongBo>
      </TenCongBo>
      <TenChuyenMucCongbo>Biệt đội phong cách</TenChuyenMucCongbo>
    </row>
    <row>
      <EXTERSTRID>T04_cc5db5b6-29f0-4c01-b69e-a765ca2ff6af</EXTERSTRID>
      <DURATION>750</DURATION>
      <COD_PROGRA>BHDBDPC_SO53_2016_4</COD_PROGRA>
      <SERIES_ID>
      </SERIES_ID>
      <SERIES_NAME>
      </SERIES_NAME>
      <EPISODE>
      </EPISODE>
      <SEASON>
      </SEASON>
      <DESCRIZIO>Biệt đội phong cách: Số 53 - 2016 (2 lần Pop up, 4 lần Logo xoay - Không chạy khi phát lại)_4</DESCRIZIO>
      <TITLE>Biệt đội phong cách: Số 53 - 2016 (2 lần Pop up, 4 lần Logo xoay - Không chạy khi phát lại)_4</TITLE>
      <ASPECT>H</ASPECT>
      <TIMECODE_I>0</TIMECODE_I>
      <TIMECODE_O>18749</TIMECODE_O>
      <DATA>18/12/2016</DATA>
      <DATA_SCAD>18/12/2017</DATA_SCAD>
      <ORA>407250</ORA>
      <NEWTYPE>BDPC</NEWTYPE>
      <TENCM>Biệt đội phong cách</TENCM>
      <NGUOISX>
      </NGUOISX>
      <DTNGUOISX>
      </DTNGUOISX>
      <GHICHU>
      </GHICHU>
      <PRODUCTION_NOTE>
      </PRODUCTION_NOTE>
      <Editor_Name>
      </Editor_Name>
      <TRANGTHAI>1</TRANGTHAI>
      <NGUOITH>
      </NGUOITH>
      <NGAYTH>
      </NGAYTH>
      <HTPS>1</HTPS>
      <LUU>
      </LUU>
      <KIEU>0</KIEU>
      <CRAWL_DESC>[Aspect Conversion] Code=4 [MediaSet]</CRAWL_DESC>
      <NOTES>
      </NOTES>
      <DOHOA>
      </DOHOA>
      <MADVSX>
      </MADVSX>
      <TENDVSX>
      </TENDVSX>
      <KENHPS>VTV6</KENHPS>
      <KENHPSHT>VTV6</KENHPSHT>
      <DUYET>0</DUYET>
      <LUUTULIEU>true</LUUTULIEU>
      <NGUONTULIEU>0</NGUONTULIEU>
      <QC>True</QC>
      <SOLANQC>0</SOLANQC>
      <TenCongBo>
      </TenCongBo>
      <TenChuyenMucCongbo>Biệt đội phong cách</TenChuyenMucCongbo>
    </row>
    <row>
      <EXTERSTRID>T0_cd49196a-d778-42cd-892a-07c27f8c74ca</EXTERSTRID>
      <DURATION>43975</DURATION>
      <COD_PROGRA>KGKPTG_XUONGCHEBIEN_14</COD_PROGRA>
      <SERIES_ID>
      </SERIES_ID>
      <SERIES_NAME>
      </SERIES_NAME>
      <EPISODE>
      </EPISODE>
      <SEASON>
      </SEASON>
      <DESCRIZIO>Khám phá thế giới: Xưởng chế biến thực phẩm của Jimmy - Phần  14/14</DESCRIZIO>
      <TITLE>Khám phá thế giới: Xưởng chế biến thực phẩm của Jimmy - Phần  14/14</TITLE>
      <ASPECT>H</ASPECT>
      <TIMECODE_I>0</TIMECODE_I>
      <TIMECODE_O>43974</TIMECODE_O>
      <DATA>18/12/2016</DATA>
      <DATA_SCAD>16/12/2026</DATA_SCAD>
      <ORA>472500</ORA>
      <NEWTYPE>KPTG</NEWTYPE>
      <TENCM>Khám phá thế giới</TENCM>
      <NGUOISX>Quản Vân Anh</NGUOISX>
      <DTNGUOISX>0913275549</DTNGUOISX>
      <GHICHU>
      </GHICHU>
      <PRODUCTION_NOTE>
      </PRODUCTION_NOTE>
      <Editor_Name>
      </Editor_Name>
      <TRANGTHAI>1</TRANGTHAI>
      <NGUOITH>
      </NGUOITH>
      <NGAYTH>
      </NGAYTH>
      <HTPS>1</HTPS>
      <LUU>
      </LUU>
      <KIEU>0</KIEU>
      <CRAWL_DESC>[Aspect Conversion] Code=4 [MediaSet]</CRAWL_DESC>
      <NOTES>
      </NOTES>
      <DOHOA>
      </DOHOA>
      <MADVSX>59</MADVSX>
      <TENDVSX>
      </TENDVSX>
      <KENHPS>VTV6</KENHPS>
      <KENHPSHT>VTV6</KENHPSHT>
      <DUYET>1</DUYET>
      <LUUTULIEU>true</LUUTULIEU>
      <NGUONTULIEU>0</NGUONTULIEU>
      <QC>True</QC>
      <SOLANQC>0</SOLANQC>
      <TenCongBo>Xưởng chế biến thực phẩm của Jimmy</TenCongBo>
      <TenChuyenMucCongbo>Khám phá thế giới</TenChuyenMucCongbo>
    </row>
    <row>
      <EXTERSTRID>T0_861e9508-0ea1-4920-bc54-3e0ea5aaa816</EXTERSTRID>
      <DURATION>17975</DURATION>
      <COD_PROGRA>TKBTKPVN_TAP7_16VANTAM</COD_PROGRA>
      <SERIES_ID>
      </SERIES_ID>
      <SERIES_NAME>
      </SERIES_NAME>
      <EPISODE>
      </EPISODE>
      <SEASON>
      </SEASON>
      <DESCRIZIO>Khám phá Việt Nam: Tập 7 - 16: Người giúp vạn tằm tự dệt chăn tơ</DESCRIZIO>
      <TITLE>Khám phá Việt Nam: Tập 7 - 16: Người giúp vạn tằm tự dệt chăn tơ</TITLE>
      <ASPECT>H</ASPECT>
      <TIMECODE_I>0</TIMECODE_I>
      <TIMECODE_O>17974</TIMECODE_O>
      <DATA>18/12/2016</DATA>
      <DATA_SCAD>16/12/2026</DATA_SCAD>
      <ORA>517500</ORA>
      <NEWTYPE>KPVN</NEWTYPE>
      <TENCM>Khám phá Việt Nam</TENCM>
      <NGUOISX>
      </NGUOISX>
      <DTNGUOISX>
      </DTNGUOISX>
      <GHICHU>
      </GHICHU>
      <PRODUCTION_NOTE>
      </PRODUCTION_NOTE>
      <Editor_Name>
      </Editor_Name>
      <TRANGTHAI>1</TRANGTHAI>
      <NGUOITH>
      </NGUOITH>
      <NGAYTH>
      </NGAYTH>
      <HTPS>1</HTPS>
      <LUU>
      </LUU>
      <KIEU>0</KIEU>
      <CRAWL_DESC>[Aspect Conversion] Code=4 [MediaSet]</CRAWL_DESC>
      <NOTES>
      </NOTES>
      <DOHOA>
      </DOHOA>
      <MADVSX>60</MADVSX>
      <TENDVSX>
      </TENDVSX>
      <KENHPS>VTV6</KENHPS>
      <KENHPSHT>VTV6</KENHPSHT>
      <DUYET>1</DUYET>
      <LUUTULIEU>true</LUUTULIEU>
      <NGUONTULIEU>0</NGUONTULIEU>
      <QC>True</QC>
      <SOLANQC>0</SOLANQC>
      <TenCongBo>
      </TenCongBo>
      <TenChuyenMucCongbo>Khám phá Việt Nam</TenChuyenMucCongbo>
    </row>
    <row>
      <EXTERSTRID>N1_201644</EXTERSTRID>
      <DURATION>1500</DURATION>
      <COD_PROGRA>DH.V6.HOMNAY.06H-12H</COD_PROGRA>
      <SERIES_ID>
      </SERIES_ID>
      <SERIES_NAME>
      </SERIES_NAME>
      <EPISODE>
      </EPISODE>
      <SEASON>
      </SEASON>
      <DESCRIZIO>Trôi - hôm nay - 6h00 -12h00 (Ngày HH: 31/12/2016)</DESCRIZIO>
      <TITLE>Trôi - hôm nay - 6h00 -12h00 (Ngày HH: 31/12/2016)</TITLE>
      <ASPECT>H</ASPECT>
      <TIMECODE_I>0</TIMECODE_I>
      <TIMECODE_O>1499</TIMECODE_O>
      <DATA>18/12/2016</DATA>
      <ORA>538500</ORA>
      <NEWTYPE>CDQB</NEWTYPE>
      <TENCM>Nhận diện kênh</TENCM>
      <MADVSX>
      </MADVSX>
      <TENDVSX>
      </TENDVSX>
      <NGUOISX>
      </NGUOISX>
      <DTNGUOISX>
      </DTNGUOISX>
      <GHICHU>
      </GHICHU>
      <PRODUCTION_NOTE>
      </PRODUCTION_NOTE>
      <Editor_Name>
      </Editor_Name>
      <TRANGTHAI>1</TRANGTHAI>
      <NGUOITH>
      </NGUOITH>
      <NGAYTH>
      </NGAYTH>
      <HTPS>0</HTPS>
      <LUU>
      </LUU>
      <KIEU>1</KIEU>
      <DOHOA>
      </DOHOA>
      <KENHPS>VTV6</KENHPS>
      <DUYET>1</DUYET>
      <LUUTULIEU>True</LUUTULIEU>
      <NGUONTULIEU>True</NGUONTULIEU>
      <QC>True</QC>
      <DATA_SCAD>07/01/2017</DATA_SCAD>
      <SOLANQC>0</SOLANQC>
      <TenCongBo>
      </TenCongBo>
      <TenChuyenMucCongbo>
      </TenChuyenMucCongbo>
    </row>
    <row>
      <EXTERSTRID>T0_6a979864-1a78-4cb8-8199-394a3303ce81</EXTERSTRID>
      <DURATION>45900</DURATION>
      <COD_PROGRA>TTNSRTL_LAMGIAUTUBOTNGHEKOLOGO</COD_PROGRA>
      <SERIES_ID>
      </SERIES_ID>
      <SERIES_NAME>
      </SERIES_NAME>
      <EPISODE>
      </EPISODE>
      <SEASON>
      </SEASON>
      <DESCRIZIO>Sinh ra từ làng: Làm giàu từ bột nghệ (Không Logo)</DESCRIZIO>
      <TITLE>Sinh ra từ làng: Làm giàu từ bột nghệ (Không Logo)</TITLE>
      <ASPECT>H</ASPECT>
      <TIMECODE_I>0</TIMECODE_I>
      <TIMECODE_O>45899</TIMECODE_O>
      <DATA>18/12/2016</DATA>
      <DATA_SCAD>16/06/2017</DATA_SCAD>
      <ORA>540000</ORA>
      <NEWTYPE>SRTL</NEWTYPE>
      <TENCM>Sinh ra từ làng</TENCM>
      <NGUOISX>
      </NGUOISX>
      <DTNGUOISX>
      </DTNGUOISX>
      <GHICHU>
      </GHICHU>
      <PRODUCTION_NOTE>
      </PRODUCTION_NOTE>
      <Editor_Name>
      </Editor_Name>
      <TRANGTHAI>1</TRANGTHAI>
      <NGUOITH>
      </NGUOITH>
      <NGAYTH>
      </NGAYTH>
      <HTPS>1</HTPS>
      <LUU>
      </LUU>
      <KIEU>0</KIEU>
      <CRAWL_DESC>[Aspect Conversion] Code=4 [MediaSet]</CRAWL_DESC>
      <NOTES>
      </NOTES>
      <DOHOA>
      </DOHOA>
      <MADVSX>87</MADVSX>
      <TENDVSX>
      </TENDVSX>
      <KENHPS>VTV6</KENHPS>
      <KENHPSHT>VTV6</KENHPSHT>
      <DUYET>1</DUYET>
      <LUUTULIEU>true</LUUTULIEU>
      <NGUONTULIEU>0</NGUONTULIEU>
      <QC>True</QC>
      <SOLANQC>0</SOLANQC>
      <TenCongBo>Làm giàu từ bột nghệ</TenCongBo>
      <TenChuyenMucCongbo>Sinh ra từ làng</TenChuyenMucCongbo>
    </row>
    <row>
      <EXTERSTRID>T0_07046dd2-6fab-48c1-99ae-d3286205470a</EXTERSTRID>
      <DURATION>45000</DURATION>
      <COD_PROGRA>TTNBXHH_SO167</COD_PROGRA>
      <SERIES_ID>
      </SERIES_ID>
      <SERIES_NAME>
      </SERIES_NAME>
      <EPISODE>
      </EPISODE>
      <SEASON>
      </SEASON>
      <DESCRIZIO>Bảng xếp hạng âm nhạc Hàn Quốc - M! Countdown: Số 167</DESCRIZIO>
      <TITLE>Bảng xếp hạng âm nhạc Hàn Quốc - M! Countdown: Số 167</TITLE>
      <ASPECT>H</ASPECT>
      <TIMECODE_I>0</TIMECODE_I>
      <TIMECODE_O>44999</TIMECODE_O>
      <DATA>18/12/2016</DATA>
      <DATA_SCAD>15/08/2017</DATA_SCAD>
      <ORA>585000</ORA>
      <NEWTYPE>BXHH</NEWTYPE>
      <TENCM>Bảng xếp hạng âm nhạc Hàn Quốc - M! Countdown</TENCM>
      <NGUOISX>
      </NGUOISX>
      <DTNGUOISX>
      </DTNGUOISX>
      <GHICHU>
      </GHICHU>
      <PRODUCTION_NOTE>
      </PRODUCTION_NOTE>
      <Editor_Name>
      </Editor_Name>
      <TRANGTHAI>1</TRANGTHAI>
      <NGUOITH>
      </NGUOITH>
      <NGAYTH>
      </NGAYTH>
      <HTPS>1</HTPS>
      <LUU>
      </LUU>
      <KIEU>0</KIEU>
      <CRAWL_DESC>[Aspect Conversion] Code=4 [MediaSet]</CRAWL_DESC>
      <NOTES>
      </NOTES>
      <DOHOA>
      </DOHOA>
      <MADVSX>87</MADVSX>
      <TENDVSX>
      </TENDVSX>
      <KENHPS>VTV6</KENHPS>
      <KENHPSHT>VTV6</KENHPSHT>
      <DUYET>1</DUYET>
      <LUUTULIEU>true</LUUTULIEU>
      <NGUONTULIEU>0</NGUONTULIEU>
      <QC>True</QC>
      <SOLANQC>0</SOLANQC>
      <TenCongBo>
      </TenCongBo>
      <TenChuyenMucCongbo>Bảng xếp hạng âm nhạc Hàn Quốc</TenChuyenMucCongbo>
    </row>
    <row>
      <EXTERSTRID>T0_4c82ae9e-a6b6-485f-b297-778a84c87ae1</EXTERSTRID>
      <DURATION>292500</DURATION>
      <COD_PROGRA>SXTTTHTT_16AFFCUPCKTHAI_INDO</COD_PROGRA>
      <SERIES_ID>
      </SERIES_ID>
      <SERIES_NAME>
      </SERIES_NAME>
      <EPISODE>
      </EPISODE>
      <SEASON>
      </SEASON>
      <DESCRIZIO>Thể thao: Giải bóng đá vô địch Đông Nam Á 2016 AFF Cup: Trận chung kết lượt về: Thái Lan - Indonesia</DESCRIZIO>
      <TITLE>Thể thao: Giải bóng đá vô địch Đông Nam Á 2016 AFF Cup: Trận chung kết lượt về: Thái Lan - Indonesia</TITLE>
      <ASPECT>H</ASPECT>
      <TIMECODE_I>0</TIMECODE_I>
      <TIMECODE_O>292499</TIMECODE_O>
      <DATA>18/12/2016</DATA>
      <DATA_SCAD>16/06/2017</DATA_SCAD>
      <ORA>630000</ORA>
      <NEWTYPE>TT</NEWTYPE>
      <TENCM>Thể thao</TENCM>
      <NGUOISX>
      </NGUOISX>
      <DTNGUOISX>
      </DTNGUOISX>
      <GHICHU>
      </GHICHU>
      <PRODUCTION_NOTE>
      </PRODUCTION_NOTE>
      <Editor_Name>
      </Editor_Name>
      <TRANGTHAI>1</TRANGTHAI>
      <NGUOITH>
      </NGUOITH>
      <NGAYTH>
      </NGAYTH>
      <HTPS>1</HTPS>
      <LUU>
      </LUU>
      <KIEU>0</KIEU>
      <CRAWL_DESC>[Aspect Conversion] Code=4 [MediaSet]</CRAWL_DESC>
      <NOTES>
      </NOTES>
      <DOHOA>
      </DOHOA>
      <MADVSX>129</MADVSX>
      <TENDVSX>
      </TENDVSX>
      <KENHPS>VTV6</KENHPS>
      <KENHPSHT>VTV6</KENHPSHT>
      <DUYET>0</DUYET>
      <LUUTULIEU>true</LUUTULIEU>
      <NGUONTULIEU>0</NGUONTULIEU>
      <QC>True</QC>
      <SOLANQC>0</SOLANQC>
      <TenCongBo>Giải bóng đá vô địch Đông Nam Á 2016 AFF Cup: Trận chung kết lượt về: Thái Lan - Indonesia</TenCongBo>
      <TenChuyenMucCongbo>Thể thao</TenChuyenMucCongbo>
    </row>
    <row>
      <EXTERSTRID>T0_39c5a83f-ba78-46c2-8ec2-9916e04420f2</EXTERSTRID>
      <DURATION>41850</DURATION>
      <COD_PROGRA>TTNHNAD_SO58</COD_PROGRA>
      <SERIES_ID>
      </SERIES_ID>
      <SERIES_NAME>
      </SERIES_NAME>
      <EPISODE>
      </EPISODE>
      <SEASON>
      </SEASON>
      <DESCRIZIO>Hôm nay ai đến?: Số 58</DESCRIZIO>
      <TITLE>Hôm nay ai đến?: Số 58</TITLE>
      <ASPECT>H</ASPECT>
      <TIMECODE_I>0</TIMECODE_I>
      <TIMECODE_O>41849</TIMECODE_O>
      <DATA>18/12/2016</DATA>
      <DATA_SCAD>18/12/2017</DATA_SCAD>
      <ORA>765000</ORA>
      <NEWTYPE>HNAD</NEWTYPE>
      <TENCM>Hôm nay ai đến?</TENCM>
      <NGUOISX>
      </NGUOISX>
      <DTNGUOISX>
      </DTNGUOISX>
      <GHICHU>
      </GHICHU>
      <PRODUCTION_NOTE>
      </PRODUCTION_NOTE>
      <Editor_Name>
      </Editor_Name>
      <TRANGTHAI>1</TRANGTHAI>
      <NGUOITH>
      </NGUOITH>
      <NGAYTH>
      </NGAYTH>
      <HTPS>1</HTPS>
      <LUU>
      </LUU>
      <KIEU>0</KIEU>
      <CRAWL_DESC>[Aspect Conversion] Code=4 [MediaSet]</CRAWL_DESC>
      <NOTES>
      </NOTES>
      <DOHOA>
      </DOHOA>
      <MADVSX>87</MADVSX>
      <TENDVSX>
      </TENDVSX>
      <KENHPS>VTV6</KENHPS>
      <KENHPSHT>VTV6</KENHPSHT>
      <DUYET>1</DUYET>
      <LUUTULIEU>true</LUUTULIEU>
      <NGUONTULIEU>0</NGUONTULIEU>
      <QC>True</QC>
      <SOLANQC>0</SOLANQC>
      <TenCongBo>
      </TenCongBo>
      <TenChuyenMucCongbo>Hôm nay ai đến?</TenChuyenMucCongbo>
    </row>
    <row>
      <EXTERSTRID>T0_956a35de-1b9d-4a7c-8de9-f69cd2b4765b</EXTERSTRID>
      <DURATION>45000</DURATION>
      <COD_PROGRA>TTNBXHH_SO168</COD_PROGRA>
      <SERIES_ID>
      </SERIES_ID>
      <SERIES_NAME>
      </SERIES_NAME>
      <EPISODE>
      </EPISODE>
      <SEASON>
      </SEASON>
      <DESCRIZIO>Bảng xếp hạng âm nhạc Hàn Quốc - M! Countdown: Số 168</DESCRIZIO>
      <TITLE>Bảng xếp hạng âm nhạc Hàn Quốc - M! Countdown: Số 168</TITLE>
      <ASPECT>H</ASPECT>
      <TIMECODE_I>0</TIMECODE_I>
      <TIMECODE_O>44999</TIMECODE_O>
      <DATA>18/12/2016</DATA>
      <DATA_SCAD>15/08/2017</DATA_SCAD>
      <ORA>810000</ORA>
      <NEWTYPE>BXHH</NEWTYPE>
      <TENCM>Bảng xếp hạng âm nhạc Hàn Quốc - M! Countdown</TENCM>
      <NGUOISX>
      </NGUOISX>
      <DTNGUOISX>
      </DTNGUOISX>
      <GHICHU>
      </GHICHU>
      <PRODUCTION_NOTE>
      </PRODUCTION_NOTE>
      <Editor_Name>
      </Editor_Name>
      <TRANGTHAI>1</TRANGTHAI>
      <NGUOITH>
      </NGUOITH>
      <NGAYTH>
      </NGAYTH>
      <HTPS>0</HTPS>
      <LUU>
      </LUU>
      <KIEU>0</KIEU>
      <CRAWL_DESC>[Aspect Conversion] Code=4 [MediaSet]</CRAWL_DESC>
      <NOTES>
      </NOTES>
      <DOHOA>
      </DOHOA>
      <MADVSX>87</MADVSX>
      <TENDVSX>
      </TENDVSX>
      <KENHPS>VTV6</KENHPS>
      <KENHPSHT>VTV6</KENHPSHT>
      <DUYET>1</DUYET>
      <LUUTULIEU>true</LUUTULIEU>
      <NGUONTULIEU>0</NGUONTULIEU>
      <QC>True</QC>
      <SOLANQC>0</SOLANQC>
      <TenCongBo>
      </TenCongBo>
      <TenChuyenMucCongbo>Bảng xếp hạng âm nhạc Hàn Quốc</TenChuyenMucCongbo>
    </row>
    <row>
      <EXTERSTRID>T0_f3a26b07-ac9c-485b-b5f8-de7782fc2e5c</EXTERSTRID>
      <DURATION>1500</DURATION>
      <COD_PROGRA>9H30_VTV6_18122016_0925</COD_PROGRA>
      <SERIES_ID>
      </SERIES_ID>
      <SERIES_NAME>
      </SERIES_NAME>
      <EPISODE>
      </EPISODE>
      <SEASON>
      </SEASON>
      <DESCRIZIO>Thời tiết V6 9h30: Thời tiết V6 9h30</DESCRIZIO>
      <TITLE>Thời tiết V6 9h30: Thời tiết V6 9h30</TITLE>
      <ASPECT>H</ASPECT>
      <TIMECODE_I>0</TIMECODE_I>
      <TIMECODE_O>1499</TIMECODE_O>
      <DATA>18/12/2016</DATA>
      <DATA_SCAD>22/12/2016</DATA_SCAD>
      <ORA>847500</ORA>
      <NEWTYPE>9H30</NEWTYPE>
      <TENCM>Thời tiết V6 9h30</TENCM>
      <NGUOISX>
      </NGUOISX>
      <DTNGUOISX>
      </DTNGUOISX>
      <GHICHU>
      </GHICHU>
      <PRODUCTION_NOTE>
      </PRODUCTION_NOTE>
      <Editor_Name>
      </Editor_Name>
      <TRANGTHAI>1</TRANGTHAI>
      <NGUOITH>
      </NGUOITH>
      <NGAYTH>
      </NGAYTH>
      <HTPS>0</HTPS>
      <LUU>
      </LUU>
      <KIEU>5</KIEU>
      <CRAWL_DESC>[Aspect Conversion] Code=4 [MediaSet]</CRAWL_DESC>
      <NOTES>
      </NOTES>
      <DOHOA>
      </DOHOA>
      <MADVSX>0</MADVSX>
      <TENDVSX>
      </TENDVSX>
      <KENHPS>VTV6</KENHPS>
      <KENHPSHT>VTV6</KENHPSHT>
      <DUYET>0</DUYET>
      <LUUTULIEU>true</LUUTULIEU>
      <NGUONTULIEU>0</NGUONTULIEU>
      <QC>True</QC>
      <SOLANQC>0</SOLANQC>
      <TenCongBo>
      </TenCongBo>
      <TenChuyenMucCongbo>Thời tiết</TenChuyenMucCongbo>
    </row>
    <row>
      <EXTERSTRID>T01_66cb52a5-aeb3-40de-870d-e4549231c4e1</EXTERSTRID>
      <DURATION>750</DURATION>
      <COD_PROGRA>BHDBDPC_SO53_2016</COD_PROGRA>
      <SERIES_ID>
      </SERIES_ID>
      <SERIES_NAME>
      </SERIES_NAME>
      <EPISODE>
      </EPISODE>
      <SEASON>
      </SEASON>
      <DESCRIZIO>Biệt đội phong cách: Số 53 - 2016 (2 lần Pop up, 4 lần Logo xoay - Không chạy khi phát lại)_1</DESCRIZIO>
      <TITLE>Biệt đội phong cách: Số 53 - 2016 (2 lần Pop up, 4 lần Logo xoay - Không chạy khi phát lại)_1</TITLE>
      <ASPECT>H</ASPECT>
      <TIMECODE_I>0</TIMECODE_I>
      <TIMECODE_O>18749</TIMECODE_O>
      <DATA>18/12/2016</DATA>
      <DATA_SCAD>18/12/2017</DATA_SCAD>
      <ORA>855000</ORA>
      <NEWTYPE>BDPC</NEWTYPE>
      <TENCM>Biệt đội phong cách</TENCM>
      <NGUOISX>
      </NGUOISX>
      <DTNGUOISX>
      </DTNGUOISX>
      <GHICHU>
      </GHICHU>
      <PRODUCTION_NOTE>
      </PRODUCTION_NOTE>
      <Editor_Name>
      </Editor_Name>
      <TRANGTHAI>1</TRANGTHAI>
      <NGUOITH>
      </NGUOITH>
      <NGAYTH>
      </NGAYTH>
      <HTPS>1</HTPS>
      <LUU>
      </LUU>
      <KIEU>0</KIEU>
      <CRAWL_DESC>[Aspect Conversion] Code=4 [MediaSet]</CRAWL_DESC>
      <NOTES>
      </NOTES>
      <DOHOA>
      </DOHOA>
      <MADVSX>
      </MADVSX>
      <TENDVSX>
      </TENDVSX>
      <KENHPS>VTV6</KENHPS>
      <KENHPSHT>VTV6</KENHPSHT>
      <DUYET>0</DUYET>
      <LUUTULIEU>true</LUUTULIEU>
      <NGUONTULIEU>0</NGUONTULIEU>
      <QC>True</QC>
      <SOLANQC>0</SOLANQC>
      <TenCongBo>
      </TenCongBo>
      <TenChuyenMucCongbo>Biệt đội phong cách</TenChuyenMucCongbo>
    </row>
    <row>
      <EXTERSTRID>T02_66cb52a5-aeb3-40de-870d-e4549231c4e1</EXTERSTRID>
      <DURATION>750</DURATION>
      <COD_PROGRA>BHDBDPC_SO53_2016_2</COD_PROGRA>
      <SERIES_ID>
      </SERIES_ID>
      <SERIES_NAME>
      </SERIES_NAME>
      <EPISODE>
      </EPISODE>
      <SEASON>
      </SEASON>
      <DESCRIZIO>Biệt đội phong cách: Số 53 - 2016 (2 lần Pop up, 4 lần Logo xoay - Không chạy khi phát lại)_2</DESCRIZIO>
      <TITLE>Biệt đội phong cách: Số 53 - 2016 (2 lần Pop up, 4 lần Logo xoay - Không chạy khi phát lại)_2</TITLE>
      <ASPECT>H</ASPECT>
      <TIMECODE_I>0</TIMECODE_I>
      <TIMECODE_O>18749</TIMECODE_O>
      <DATA>18/12/2016</DATA>
      <DATA_SCAD>18/12/2017</DATA_SCAD>
      <ORA>855750</ORA>
      <NEWTYPE>BDPC</NEWTYPE>
      <TENCM>Biệt đội phong cách</TENCM>
      <NGUOISX>
      </NGUOISX>
      <DTNGUOISX>
      </DTNGUOISX>
      <GHICHU>
      </GHICHU>
      <PRODUCTION_NOTE>
      </PRODUCTION_NOTE>
      <Editor_Name>
      </Editor_Name>
      <TRANGTHAI>1</TRANGTHAI>
      <NGUOITH>
      </NGUOITH>
      <NGAYTH>
      </NGAYTH>
      <HTPS>1</HTPS>
      <LUU>
      </LUU>
      <KIEU>0</KIEU>
      <CRAWL_DESC>[Aspect Conversion] Code=4 [MediaSet]</CRAWL_DESC>
      <NOTES>
      </NOTES>
      <DOHOA>
      </DOHOA>
      <MADVSX>
      </MADVSX>
      <TENDVSX>
      </TENDVSX>
      <KENHPS>VTV6</KENHPS>
      <KENHPSHT>VTV6</KENHPSHT>
      <DUYET>0</DUYET>
      <LUUTULIEU>true</LUUTULIEU>
      <NGUONTULIEU>0</NGUONTULIEU>
      <QC>True</QC>
      <SOLANQC>0</SOLANQC>
      <TenCongBo>
      </TenCongBo>
      <TenChuyenMucCongbo>Biệt đội phong cách</TenChuyenMucCongbo>
    </row>
    <row>
      <EXTERSTRID>T03_66cb52a5-aeb3-40de-870d-e4549231c4e1</EXTERSTRID>
      <DURATION>750</DURATION>
      <COD_PROGRA>BHDBDPC_SO53_2016_3</COD_PROGRA>
      <SERIES_ID>
      </SERIES_ID>
      <SERIES_NAME>
      </SERIES_NAME>
      <EPISODE>
      </EPISODE>
      <SEASON>
      </SEASON>
      <DESCRIZIO>Biệt đội phong cách: Số 53 - 2016 (2 lần Pop up, 4 lần Logo xoay - Không chạy khi phát lại)_3</DESCRIZIO>
      <TITLE>Biệt đội phong cách: Số 53 - 2016 (2 lần Pop up, 4 lần Logo xoay - Không chạy khi phát lại)_3</TITLE>
      <ASPECT>H</ASPECT>
      <TIMECODE_I>0</TIMECODE_I>
      <TIMECODE_O>18749</TIMECODE_O>
      <DATA>18/12/2016</DATA>
      <DATA_SCAD>18/12/2017</DATA_SCAD>
      <ORA>856500</ORA>
      <NEWTYPE>BDPC</NEWTYPE>
      <TENCM>Biệt đội phong cách</TENCM>
      <NGUOISX>
      </NGUOISX>
      <DTNGUOISX>
      </DTNGUOISX>
      <GHICHU>
      </GHICHU>
      <PRODUCTION_NOTE>
      </PRODUCTION_NOTE>
      <Editor_Name>
      </Editor_Name>
      <TRANGTHAI>1</TRANGTHAI>
      <NGUOITH>
      </NGUOITH>
      <NGAYTH>
      </NGAYTH>
      <HTPS>1</HTPS>
      <LUU>
      </LUU>
      <KIEU>0</KIEU>
      <CRAWL_DESC>[Aspect Conversion] Code=4 [MediaSet]</CRAWL_DESC>
      <NOTES>
      </NOTES>
      <DOHOA>
      </DOHOA>
      <MADVSX>
      </MADVSX>
      <TENDVSX>
      </TENDVSX>
      <KENHPS>VTV6</KENHPS>
      <KENHPSHT>VTV6</KENHPSHT>
      <DUYET>0</DUYET>
      <LUUTULIEU>true</LUUTULIEU>
      <NGUONTULIEU>0</NGUONTULIEU>
      <QC>True</QC>
      <SOLANQC>0</SOLANQC>
      <TenCongBo>
      </TenCongBo>
      <TenChuyenMucCongbo>Biệt đội phong cách</TenChuyenMucCongbo>
    </row>
    <row>
      <EXTERSTRID>T04_66cb52a5-aeb3-40de-870d-e4549231c4e1</EXTERSTRID>
      <DURATION>750</DURATION>
      <COD_PROGRA>BHDBDPC_SO53_2016_4</COD_PROGRA>
      <SERIES_ID>
      </SERIES_ID>
      <SERIES_NAME>
      </SERIES_NAME>
      <EPISODE>
      </EPISODE>
      <SEASON>
      </SEASON>
      <DESCRIZIO>Biệt đội phong cách: Số 53 - 2016 (2 lần Pop up, 4 lần Logo xoay - Không chạy khi phát lại)_4</DESCRIZIO>
      <TITLE>Biệt đội phong cách: Số 53 - 2016 (2 lần Pop up, 4 lần Logo xoay - Không chạy khi phát lại)_4</TITLE>
      <ASPECT>H</ASPECT>
      <TIMECODE_I>0</TIMECODE_I>
      <TIMECODE_O>18749</TIMECODE_O>
      <DATA>18/12/2016</DATA>
      <DATA_SCAD>18/12/2017</DATA_SCAD>
      <ORA>857250</ORA>
      <NEWTYPE>BDPC</NEWTYPE>
      <TENCM>Biệt đội phong cách</TENCM>
      <NGUOISX>
      </NGUOISX>
      <DTNGUOISX>
      </DTNGUOISX>
      <GHICHU>
      </GHICHU>
      <PRODUCTION_NOTE>
      </PRODUCTION_NOTE>
      <Editor_Name>
      </Editor_Name>
      <TRANGTHAI>1</TRANGTHAI>
      <NGUOITH>
      </NGUOITH>
      <NGAYTH>
      </NGAYTH>
      <HTPS>1</HTPS>
      <LUU>
      </LUU>
      <KIEU>0</KIEU>
      <CRAWL_DESC>[Aspect Conversion] Code=4 [MediaSet]</CRAWL_DESC>
      <NOTES>
      </NOTES>
      <DOHOA>
      </DOHOA>
      <MADVSX>
      </MADVSX>
      <TENDVSX>
      </TENDVSX>
      <KENHPS>VTV6</KENHPS>
      <KENHPSHT>VTV6</KENHPSHT>
      <DUYET>0</DUYET>
      <LUUTULIEU>true</LUUTULIEU>
      <NGUONTULIEU>0</NGUONTULIEU>
      <QC>True</QC>
      <SOLANQC>0</SOLANQC>
      <TenCongBo>
      </TenCongBo>
      <TenChuyenMucCongbo>Biệt đội phong cách</TenChuyenMucCongbo>
    </row>
    <row>
      <EXTERSTRID>T0_8b0b41c0-710b-4d04-8c6d-adfa2f281311</EXTERSTRID>
      <DURATION>18575</DURATION>
      <COD_PROGRA>TTNKVVN_SO422016</COD_PROGRA>
      <SERIES_ID>
      </SERIES_ID>
      <SERIES_NAME>
      </SERIES_NAME>
      <EPISODE>
      </EPISODE>
      <SEASON>
      </SEASON>
      <DESCRIZIO>Khát vọng Việt Nam: Số 42/2016</DESCRIZIO>
      <TITLE>Khát vọng Việt Nam: Số 42/2016</TITLE>
      <ASPECT>H</ASPECT>
      <TIMECODE_I>0</TIMECODE_I>
      <TIMECODE_O>18574</TIMECODE_O>
      <DATA>18/12/2016</DATA>
      <DATA_SCAD>18/12/2017</DATA_SCAD>
      <ORA>930000</ORA>
      <NEWTYPE>KVVN</NEWTYPE>
      <TENCM>Khát vọng Việt Nam</TENCM>
      <NGUOISX>
      </NGUOISX>
      <DTNGUOISX>
      </DTNGUOISX>
      <GHICHU>
      </GHICHU>
      <PRODUCTION_NOTE>
      </PRODUCTION_NOTE>
      <Editor_Name>
      </Editor_Name>
      <TRANGTHAI>1</TRANGTHAI>
      <NGUOITH>
      </NGUOITH>
      <NGAYTH>
      </NGAYTH>
      <HTPS>1</HTPS>
      <LUU>
      </LUU>
      <KIEU>0</KIEU>
      <CRAWL_DESC>[Aspect Conversion] Code=4 [MediaSet]</CRAWL_DESC>
      <NOTES>
      </NOTES>
      <DOHOA>
      </DOHOA>
      <MADVSX>87</MADVSX>
      <TENDVSX>
      </TENDVSX>
      <KENHPS>VTV6</KENHPS>
      <KENHPSHT>VTV6</KENHPSHT>
      <DUYET>1</DUYET>
      <LUUTULIEU>true</LUUTULIEU>
      <NGUONTULIEU>0</NGUONTULIEU>
      <QC>True</QC>
      <SOLANQC>0</SOLANQC>
      <TenCongBo>
      </TenCongBo>
      <TenChuyenMucCongbo>Khát vọng Việt Nam</TenChuyenMucCongbo>
    </row>
    <row>
      <EXTERSTRID>T0_4192760b-2600-4506-9291-7d8b24bbbb8e</EXTERSTRID>
      <DURATION>45000</DURATION>
      <COD_PROGRA>TTNNBHN_CAROVACHAMBI_SO512016</COD_PROGRA>
      <SERIES_ID>
      </SERIES_ID>
      <SERIES_NAME>
      </SERIES_NAME>
      <EPISODE>
      </EPISODE>
      <SEASON>
      </SEASON>
      <DESCRIZIO>Những bông hoa nhỏ: Caro và Chấm bi - Số 51/2016</DESCRIZIO>
      <TITLE>Những bông hoa nhỏ: Caro và Chấm bi - Số 51/2016</TITLE>
      <ASPECT>H</ASPECT>
      <TIMECODE_I>0</TIMECODE_I>
      <TIMECODE_O>44999</TIMECODE_O>
      <DATA>18/12/2016</DATA>
      <DATA_SCAD>16/06/2017</DATA_SCAD>
      <ORA>945000</ORA>
      <NEWTYPE>NBHN</NEWTYPE>
      <TENCM>Những bông hoa nhỏ</TENCM>
      <NGUOISX>
      </NGUOISX>
      <DTNGUOISX>
      </DTNGUOISX>
      <GHICHU>
      </GHICHU>
      <PRODUCTION_NOTE>
      </PRODUCTION_NOTE>
      <Editor_Name>
      </Editor_Name>
      <TRANGTHAI>1</TRANGTHAI>
      <NGUOITH>
      </NGUOITH>
      <NGAYTH>
      </NGAYTH>
      <HTPS>0</HTPS>
      <LUU>
      </LUU>
      <KIEU>0</KIEU>
      <CRAWL_DESC>[Aspect Conversion] Code=4 [MediaSet]</CRAWL_DESC>
      <NOTES>
      </NOTES>
      <DOHOA>
      </DOHOA>
      <MADVSX>87</MADVSX>
      <TENDVSX>
      </TENDVSX>
      <KENHPS>VTV6</KENHPS>
      <KENHPSHT>VTV6</KENHPSHT>
      <DUYET>1</DUYET>
      <LUUTULIEU>true</LUUTULIEU>
      <NGUONTULIEU>0</NGUONTULIEU>
      <QC>True</QC>
      <SOLANQC>0</SOLANQC>
      <TenCongBo>Caro và Chấm bi </TenCongBo>
      <TenChuyenMucCongbo>Những bông hoa nhỏ</TenChuyenMucCongbo>
    </row>
    <row>
      <EXTERSTRID>T0_323fe788-3d5d-4560-8793-cd3231927b85</EXTERSTRID>
      <DURATION>45775</DURATION>
      <COD_PROGRA>TTNGKT_DIEUHUONG</COD_PROGRA>
      <SERIES_ID>
      </SERIES_ID>
      <SERIES_NAME>
      </SERIES_NAME>
      <EPISODE>
      </EPISODE>
      <SEASON>
      </SEASON>
      <DESCRIZIO>Ghế không tựa: Diệu Hương</DESCRIZIO>
      <TITLE>Ghế không tựa: Diệu Hương</TITLE>
      <ASPECT>H</ASPECT>
      <TIMECODE_I>0</TIMECODE_I>
      <TIMECODE_O>45774</TIMECODE_O>
      <DATA>18/12/2016</DATA>
      <DATA_SCAD>15/08/2017</DATA_SCAD>
      <ORA>990000</ORA>
      <NEWTYPE>GKT</NEWTYPE>
      <TENCM>Ghế không tựa</TENCM>
      <NGUOISX>
      </NGUOISX>
      <DTNGUOISX>
      </DTNGUOISX>
      <GHICHU>
      </GHICHU>
      <PRODUCTION_NOTE>
      </PRODUCTION_NOTE>
      <Editor_Name>
      </Editor_Name>
      <TRANGTHAI>1</TRANGTHAI>
      <NGUOITH>
      </NGUOITH>
      <NGAYTH>
      </NGAYTH>
      <HTPS>0</HTPS>
      <LUU>
      </LUU>
      <KIEU>0</KIEU>
      <CRAWL_DESC>[Aspect Conversion] Code=4 [MediaSet]</CRAWL_DESC>
      <NOTES>
      </NOTES>
      <DOHOA>
      </DOHOA>
      <MADVSX>87</MADVSX>
      <TENDVSX>
      </TENDVSX>
      <KENHPS>VTV6</KENHPS>
      <KENHPSHT>VTV6</KENHPSHT>
      <DUYET>1</DUYET>
      <LUUTULIEU>true</LUUTULIEU>
      <NGUONTULIEU>0</NGUONTULIEU>
      <QC>True</QC>
      <SOLANQC>0</SOLANQC>
      <TenCongBo>
      </TenCongBo>
      <TenChuyenMucCongbo>Ghế không tựa</TenChuyenMucCongbo>
    </row>
    <row>
      <EXTERSTRID>T0_0ee187e0-fc47-4ae1-baac-56420004d117</EXTERSTRID>
      <DURATION>41775</DURATION>
      <COD_PROGRA>TTNNC_CONDUONGTOIDI</COD_PROGRA>
      <SERIES_ID>
      </SERIES_ID>
      <SERIES_NAME>
      </SERIES_NAME>
      <EPISODE>
      </EPISODE>
      <SEASON>
      </SEASON>
      <DESCRIZIO>Ngược chiều: Con đường tôi đi</DESCRIZIO>
      <TITLE>Ngược chiều: Con đường tôi đi</TITLE>
      <ASPECT>H</ASPECT>
      <TIMECODE_I>0</TIMECODE_I>
      <TIMECODE_O>41774</TIMECODE_O>
      <DATA>18/12/2016</DATA>
      <DATA_SCAD>16/06/2017</DATA_SCAD>
      <ORA>1035000</ORA>
      <NEWTYPE>NC</NEWTYPE>
      <TENCM>Ngược chiều</TENCM>
      <NGUOISX>
      </NGUOISX>
      <DTNGUOISX>
      </DTNGUOISX>
      <GHICHU>
      </GHICHU>
      <PRODUCTION_NOTE>
      </PRODUCTION_NOTE>
      <Editor_Name>
      </Editor_Name>
      <TRANGTHAI>1</TRANGTHAI>
      <NGUOITH>
      </NGUOITH>
      <NGAYTH>
      </NGAYTH>
      <HTPS>1</HTPS>
      <LUU>
      </LUU>
      <KIEU>0</KIEU>
      <CRAWL_DESC>[Aspect Conversion] Code=4 [MediaSet]</CRAWL_DESC>
      <NOTES>
      </NOTES>
      <DOHOA>
      </DOHOA>
      <MADVSX>87</MADVSX>
      <TENDVSX>
      </TENDVSX>
      <KENHPS>VTV6</KENHPS>
      <KENHPSHT>VTV6</KENHPSHT>
      <DUYET>1</DUYET>
      <LUUTULIEU>true</LUUTULIEU>
      <NGUONTULIEU>0</NGUONTULIEU>
      <QC>True</QC>
      <SOLANQC>0</SOLANQC>
      <TenCongBo>Con đường tôi đi</TenCongBo>
      <TenChuyenMucCongbo>Ngược chiều</TenChuyenMucCongbo>
    </row>
    <row>
      <EXTERSTRID>T0_b9799a4d-446a-4963-9312-d64e89a4a112</EXTERSTRID>
      <DURATION>1500</DURATION>
      <COD_PROGRA>12H0_VTV6_18122016_1155</COD_PROGRA>
      <SERIES_ID>
      </SERIES_ID>
      <SERIES_NAME>
      </SERIES_NAME>
      <EPISODE>
      </EPISODE>
      <SEASON>
      </SEASON>
      <DESCRIZIO>Thời tiết V6 12h00: Thời tiết V6 12h00</DESCRIZIO>
      <TITLE>Thời tiết V6 12h00: Thời tiết V6 12h00</TITLE>
      <ASPECT>H</ASPECT>
      <TIMECODE_I>0</TIMECODE_I>
      <TIMECODE_O>1499</TIMECODE_O>
      <DATA>18/12/2016</DATA>
      <DATA_SCAD>22/12/2016</DATA_SCAD>
      <ORA>1072500</ORA>
      <NEWTYPE>12H0</NEWTYPE>
      <TENCM>Thời tiết V6 12h00</TENCM>
      <NGUOISX>
      </NGUOISX>
      <DTNGUOISX>
      </DTNGUOISX>
      <GHICHU>
      </GHICHU>
      <PRODUCTION_NOTE>
      </PRODUCTION_NOTE>
      <Editor_Name>
      </Editor_Name>
      <TRANGTHAI>1</TRANGTHAI>
      <NGUOITH>
      </NGUOITH>
      <NGAYTH>
      </NGAYTH>
      <HTPS>0</HTPS>
      <LUU>
      </LUU>
      <KIEU>5</KIEU>
      <CRAWL_DESC>[Aspect Conversion] Code=4 [MediaSet]</CRAWL_DESC>
      <NOTES>
      </NOTES>
      <DOHOA>
      </DOHOA>
      <MADVSX>0</MADVSX>
      <TENDVSX>
      </TENDVSX>
      <KENHPS>VTV6</KENHPS>
      <KENHPSHT>VTV6</KENHPSHT>
      <DUYET>0</DUYET>
      <LUUTULIEU>true</LUUTULIEU>
      <NGUONTULIEU>0</NGUONTULIEU>
      <QC>True</QC>
      <SOLANQC>0</SOLANQC>
      <TenCongBo>
      </TenCongBo>
      <TenChuyenMucCongbo>Thời tiết</TenChuyenMucCongbo>
    </row>
    <row>
      <EXTERSTRID>N1_202010</EXTERSTRID>
      <DURATION>1500</DURATION>
      <COD_PROGRA>DH.V6.HOMNAY.12H-24H</COD_PROGRA>
      <SERIES_ID>
      </SERIES_ID>
      <SERIES_NAME>
      </SERIES_NAME>
      <EPISODE>
      </EPISODE>
      <SEASON>
      </SEASON>
      <DESCRIZIO>Trôi - hôm nay - 12h00 - 24h00 (Ngày HH: 31/12/2016)</DESCRIZIO>
      <TITLE>Trôi - hôm nay - 12h00 - 24h00 (Ngày HH: 31/12/2016)</TITLE>
      <ASPECT>H</ASPECT>
      <TIMECODE_I>0</TIMECODE_I>
      <TIMECODE_O>1499</TIMECODE_O>
      <DATA>18/12/2016</DATA>
      <ORA>1078500</ORA>
      <NEWTYPE>CDQB</NEWTYPE>
      <TENCM>Nhận diện kênh</TENCM>
      <MADVSX>
      </MADVSX>
      <TENDVSX>
      </TENDVSX>
      <NGUOISX>
      </NGUOISX>
      <DTNGUOISX>
      </DTNGUOISX>
      <GHICHU>
      </GHICHU>
      <PRODUCTION_NOTE>
      </PRODUCTION_NOTE>
      <Editor_Name>
      </Editor_Name>
      <TRANGTHAI>1</TRANGTHAI>
      <NGUOITH>
      </NGUOITH>
      <NGAYTH>
      </NGAYTH>
      <HTPS>0</HTPS>
      <LUU>
      </LUU>
      <KIEU>1</KIEU>
      <DOHOA>
      </DOHOA>
      <KENHPS>VTV6</KENHPS>
      <DUYET>1</DUYET>
      <LUUTULIEU>True</LUUTULIEU>
      <NGUONTULIEU>True</NGUONTULIEU>
      <QC>True</QC>
      <DATA_SCAD>07/01/2017</DATA_SCAD>
      <SOLANQC>0</SOLANQC>
      <TenCongBo>
      </TenCongBo>
      <TenChuyenMucCongbo>
      </TenChuyenMucCongbo>
    </row>
    <row>
      <EXTERSTRID>T0_7b8702cf-d565-41ba-907a-6596772e831e</EXTERSTRID>
      <DURATION>90000</DURATION>
      <COD_PROGRA>BTVV_VTV6_18122016_1200</COD_PROGRA>
      <SERIES_ID>
      </SERIES_ID>
      <SERIES_NAME>
      </SERIES_NAME>
      <EPISODE>
      </EPISODE>
      <SEASON>
      </SEASON>
      <DESCRIZIO>Bữa trưa vui vẻ: Bữa trưa vui vẻ</DESCRIZIO>
      <TITLE>Bữa trưa vui vẻ: Bữa trưa vui vẻ</TITLE>
      <ASPECT>H</ASPECT>
      <TIMECODE_I>0</TIMECODE_I>
      <TIMECODE_O>89999</TIMECODE_O>
      <DATA>18/12/2016</DATA>
      <DATA_SCAD>15/08/2017</DATA_SCAD>
      <ORA>1080000</ORA>
      <NEWTYPE>BTVV</NEWTYPE>
      <TENCM>Bữa trưa vui vẻ</TENCM>
      <NGUOISX>
      </NGUOISX>
      <DTNGUOISX>
      </DTNGUOISX>
      <GHICHU>
      </GHICHU>
      <PRODUCTION_NOTE>
      </PRODUCTION_NOTE>
      <Editor_Name>
      </Editor_Name>
      <TRANGTHAI>1</TRANGTHAI>
      <NGUOITH>
      </NGUOITH>
      <NGAYTH>
      </NGAYTH>
      <HTPS>0</HTPS>
      <LUU>
      </LUU>
      <KIEU>0</KIEU>
      <CRAWL_DESC>[Aspect Conversion] Code=4 [MediaSet]</CRAWL_DESC>
      <NOTES>
      </NOTES>
      <DOHOA>
      </DOHOA>
      <MADVSX>0</MADVSX>
      <TENDVSX>
      </TENDVSX>
      <KENHPS>VTV6</KENHPS>
      <KENHPSHT>VTV6</KENHPSHT>
      <DUYET>0</DUYET>
      <LUUTULIEU>true</LUUTULIEU>
      <NGUONTULIEU>0</NGUONTULIEU>
      <QC>True</QC>
      <SOLANQC>0</SOLANQC>
      <TenCongBo>
      </TenCongBo>
      <TenChuyenMucCongbo>Bữa trưa vui vẻ</TenChuyenMucCongbo>
    </row>
    <row>
      <EXTERSTRID>T0_1baf4cb8-57e6-45f8-8e53-cac3c4b3f3e6</EXTERSTRID>
      <DURATION>45000</DURATION>
      <COD_PROGRA>SXTTTHAO_TAPCHIBONGDATG1812</COD_PROGRA>
      <SERIES_ID>
      </SERIES_ID>
      <SERIES_NAME>
      </SERIES_NAME>
      <EPISODE>
      </EPISODE>
      <SEASON>
      </SEASON>
      <DESCRIZIO>Thể thao 30: Tạp chí bóng đá thế giới ngày 18/12</DESCRIZIO>
      <TITLE>Thể thao 30: Tạp chí bóng đá thế giới ngày 18/12</TITLE>
      <ASPECT>H</ASPECT>
      <TIMECODE_I>0</TIMECODE_I>
      <TIMECODE_O>44999</TIMECODE_O>
      <DATA>18/12/2016</DATA>
      <DATA_SCAD>28/12/2016</DATA_SCAD>
      <ORA>1170000</ORA>
      <NEWTYPE>THAO</NEWTYPE>
      <TENCM>Thể thao 30</TENCM>
      <NGUOISX>
      </NGUOISX>
      <DTNGUOISX>
      </DTNGUOISX>
      <GHICHU>
      </GHICHU>
      <PRODUCTION_NOTE>
      </PRODUCTION_NOTE>
      <Editor_Name>
      </Editor_Name>
      <TRANGTHAI>1</TRANGTHAI>
      <NGUOITH>
      </NGUOITH>
      <NGAYTH>
      </NGAYTH>
      <HTPS>0</HTPS>
      <LUU>
      </LUU>
      <KIEU>0</KIEU>
      <CRAWL_DESC>[Aspect Conversion] Code=4 [MediaSet]</CRAWL_DESC>
      <NOTES>
      </NOTES>
      <DOHOA>
      </DOHOA>
      <MADVSX>129</MADVSX>
      <TENDVSX>
      </TENDVSX>
      <KENHPS>VTV6</KENHPS>
      <KENHPSHT>VTV6</KENHPSHT>
      <DUYET>0</DUYET>
      <LUUTULIEU>true</LUUTULIEU>
      <NGUONTULIEU>0</NGUONTULIEU>
      <QC>True</QC>
      <SOLANQC>0</SOLANQC>
      <TenCongBo>Tạp chí bóng đá thế giới</TenCongBo>
      <TenChuyenMucCongbo>Thể thao</TenChuyenMucCongbo>
    </row>
    <row>
      <EXTERSTRID>T0_7211e3c8-4aae-47be-8469-b97ade8e0ee9</EXTERSTRID>
      <DURATION>43875</DURATION>
      <COD_PROGRA>TTNHNAD_SO69</COD_PROGRA>
      <SERIES_ID>
      </SERIES_ID>
      <SERIES_NAME>
      </SERIES_NAME>
      <EPISODE>
      </EPISODE>
      <SEASON>
      </SEASON>
      <DESCRIZIO>Hôm nay ai đến?: Số 69</DESCRIZIO>
      <TITLE>Hôm nay ai đến?: Số 69</TITLE>
      <ASPECT>H</ASPECT>
      <TIMECODE_I>0</TIMECODE_I>
      <TIMECODE_O>43874</TIMECODE_O>
      <DATA>18/12/2016</DATA>
      <DATA_SCAD>18/12/2017</DATA_SCAD>
      <ORA>1215000</ORA>
      <NEWTYPE>HNAD</NEWTYPE>
      <TENCM>Hôm nay ai đến?</TENCM>
      <NGUOISX>
      </NGUOISX>
      <DTNGUOISX>
      </DTNGUOISX>
      <GHICHU>
      </GHICHU>
      <PRODUCTION_NOTE>
      </PRODUCTION_NOTE>
      <Editor_Name>
      </Editor_Name>
      <TRANGTHAI>1</TRANGTHAI>
      <NGUOITH>
      </NGUOITH>
      <NGAYTH>
      </NGAYTH>
      <HTPS>1</HTPS>
      <LUU>
      </LUU>
      <KIEU>0</KIEU>
      <CRAWL_DESC>[Aspect Conversion] Code=4 [MediaSet]</CRAWL_DESC>
      <NOTES>
      </NOTES>
      <DOHOA>
      </DOHOA>
      <MADVSX>87</MADVSX>
      <TENDVSX>
      </TENDVSX>
      <KENHPS>VTV6</KENHPS>
      <KENHPSHT>VTV6</KENHPSHT>
      <DUYET>1</DUYET>
      <LUUTULIEU>true</LUUTULIEU>
      <NGUONTULIEU>0</NGUONTULIEU>
      <QC>True</QC>
      <SOLANQC>0</SOLANQC>
      <TenCongBo>
      </TenCongBo>
      <TenChuyenMucCongbo>Hôm nay ai đến?</TenChuyenMucCongbo>
    </row>
    <row>
      <EXTERSTRID>T0_edb55e7a-2bbf-45ea-9d0f-ec9959e0be81</EXTERSTRID>
      <DURATION>63150</DURATION>
      <COD_PROGRA>TTNTTA_CHETVIDUOCYEU</COD_PROGRA>
      <SERIES_ID>
      </SERIES_ID>
      <SERIES_NAME>
      </SERIES_NAME>
      <EPISODE>
      </EPISODE>
      <SEASON>
      </SEASON>
      <DESCRIZIO>Toà tuyên án: Chết vì được yêu</DESCRIZIO>
      <TITLE>Toà tuyên án: Chết vì được yêu</TITLE>
      <ASPECT>H</ASPECT>
      <TIMECODE_I>0</TIMECODE_I>
      <TIMECODE_O>63149</TIMECODE_O>
      <DATA>18/12/2016</DATA>
      <DATA_SCAD>16/06/2017</DATA_SCAD>
      <ORA>1260000</ORA>
      <NEWTYPE>TTA</NEWTYPE>
      <TENCM>Toà tuyên án</TENCM>
      <NGUOISX>
      </NGUOISX>
      <DTNGUOISX>
      </DTNGUOISX>
      <GHICHU>
      </GHICHU>
      <PRODUCTION_NOTE>
      </PRODUCTION_NOTE>
      <Editor_Name>
      </Editor_Name>
      <TRANGTHAI>1</TRANGTHAI>
      <NGUOITH>
      </NGUOITH>
      <NGAYTH>
      </NGAYTH>
      <HTPS>1</HTPS>
      <LUU>
      </LUU>
      <KIEU>0</KIEU>
      <CRAWL_DESC>[Aspect Conversion] Code=4 [MediaSet]</CRAWL_DESC>
      <NOTES>
      </NOTES>
      <DOHOA>
      </DOHOA>
      <MADVSX>87</MADVSX>
      <TENDVSX>
      </TENDVSX>
      <KENHPS>VTV6</KENHPS>
      <KENHPSHT>VTV6</KENHPSHT>
      <DUYET>1</DUYET>
      <LUUTULIEU>true</LUUTULIEU>
      <NGUONTULIEU>0</NGUONTULIEU>
      <QC>True</QC>
      <SOLANQC>0</SOLANQC>
      <TenCongBo>
      </TenCongBo>
      <TenChuyenMucCongbo>Toà tuyên án</TenChuyenMucCongbo>
    </row>
    <row>
      <EXTERSTRID>T0_7daccd37-d680-4471-ac04-ea77c1343fa7</EXTERSTRID>
      <DURATION>15550</DURATION>
      <COD_PROGRA>TKBTVKN2_HTDIEUBIMATHH2112</COD_PROGRA>
      <SERIES_ID>
      </SERIES_ID>
      <SERIES_NAME>
      </SERIES_NAME>
      <EPISODE>
      </EPISODE>
      <SEASON>
      </SEASON>
      <DESCRIZIO>VTV kết nối: Hậu trường phim Điều bí mật (HH2112)</DESCRIZIO>
      <TITLE>VTV kết nối: Hậu trường phim Điều bí mật (HH2112)</TITLE>
      <ASPECT>H</ASPECT>
      <TIMECODE_I>0</TIMECODE_I>
      <TIMECODE_O>15549</TIMECODE_O>
      <DATA>18/12/2016</DATA>
      <DATA_SCAD>16/02/2017</DATA_SCAD>
      <ORA>1327500</ORA>
      <NEWTYPE>VKN</NEWTYPE>
      <TENCM>VTV kết nối</TENCM>
      <NGUOISX>
      </NGUOISX>
      <DTNGUOISX>
      </DTNGUOISX>
      <GHICHU>
      </GHICHU>
      <PRODUCTION_NOTE>
      </PRODUCTION_NOTE>
      <Editor_Name>
      </Editor_Name>
      <TRANGTHAI>1</TRANGTHAI>
      <NGUOITH>
      </NGUOITH>
      <NGAYTH>
      </NGAYTH>
      <HTPS>1</HTPS>
      <LUU>
      </LUU>
      <KIEU>0</KIEU>
      <CRAWL_DESC>[Aspect Conversion] Code=4 [MediaSet]</CRAWL_DESC>
      <NOTES>
      </NOTES>
      <DOHOA>
      </DOHOA>
      <MADVSX>60</MADVSX>
      <TENDVSX>
      </TENDVSX>
      <KENHPS>VTV6</KENHPS>
      <KENHPSHT>VTV6</KENHPSHT>
      <DUYET>1</DUYET>
      <LUUTULIEU>true</LUUTULIEU>
      <NGUONTULIEU>0</NGUONTULIEU>
      <QC>True</QC>
      <SOLANQC>0</SOLANQC>
      <TenCongBo>
      </TenCongBo>
      <TenChuyenMucCongbo>VTV kết nối</TenChuyenMucCongbo>
    </row>
    <row>
      <EXTERSTRID>T0_e0bff78c-2ca3-4e28-9db1-7957e8f2cfe7</EXTERSTRID>
      <DURATION>19500</DURATION>
      <COD_PROGRA>TKBTKPVN_TAP8_16</COD_PROGRA>
      <SERIES_ID>
      </SERIES_ID>
      <SERIES_NAME>
      </SERIES_NAME>
      <EPISODE>
      </EPISODE>
      <SEASON>
      </SEASON>
      <DESCRIZIO>Khám phá Việt Nam: Tập 8 - 16</DESCRIZIO>
      <TITLE>Khám phá Việt Nam: Tập 8 - 16</TITLE>
      <ASPECT>H</ASPECT>
      <TIMECODE_I>0</TIMECODE_I>
      <TIMECODE_O>19499</TIMECODE_O>
      <DATA>18/12/2016</DATA>
      <DATA_SCAD>16/12/2026</DATA_SCAD>
      <ORA>1350000</ORA>
      <NEWTYPE>KPVN</NEWTYPE>
      <TENCM>Khám phá Việt Nam</TENCM>
      <NGUOISX>
      </NGUOISX>
      <DTNGUOISX>
      </DTNGUOISX>
      <GHICHU>
      </GHICHU>
      <PRODUCTION_NOTE>
      </PRODUCTION_NOTE>
      <Editor_Name>
      </Editor_Name>
      <TRANGTHAI>1</TRANGTHAI>
      <NGUOITH>
      </NGUOITH>
      <NGAYTH>
      </NGAYTH>
      <HTPS>0</HTPS>
      <LUU>
      </LUU>
      <KIEU>0</KIEU>
      <CRAWL_DESC>[Aspect Conversion] Code=4 [MediaSet]</CRAWL_DESC>
      <NOTES>
      </NOTES>
      <DOHOA>
      </DOHOA>
      <MADVSX>60</MADVSX>
      <TENDVSX>
      </TENDVSX>
      <KENHPS>VTV6</KENHPS>
      <KENHPSHT>VTV6</KENHPSHT>
      <DUYET>1</DUYET>
      <LUUTULIEU>true</LUUTULIEU>
      <NGUONTULIEU>0</NGUONTULIEU>
      <QC>True</QC>
      <SOLANQC>0</SOLANQC>
      <TenCongBo>
      </TenCongBo>
      <TenChuyenMucCongbo>Khám phá Việt Nam</TenChuyenMucCongbo>
    </row>
    <row>
      <EXTERSTRID>T0_70f2db74-b434-44cc-aa1a-0a010f00d5ab</EXTERSTRID>
      <DURATION>23400</DURATION>
      <COD_PROGRA>KGKP_THUYDIENIALY_TAP1</COD_PROGRA>
      <SERIES_ID>
      </SERIES_ID>
      <SERIES_NAME>
      </SERIES_NAME>
      <EPISODE>
      </EPISODE>
      <SEASON>
      </SEASON>
      <DESCRIZIO>Khám phá (V6): Thủy điện Ialy - Tập 1</DESCRIZIO>
      <TITLE>Khám phá (V6): Thủy điện Ialy - Tập 1</TITLE>
      <ASPECT>H</ASPECT>
      <TIMECODE_I>0</TIMECODE_I>
      <TIMECODE_O>23399</TIMECODE_O>
      <DATA>18/12/2016</DATA>
      <DATA_SCAD>16/12/2026</DATA_SCAD>
      <ORA>1372500</ORA>
      <NEWTYPE>KP</NEWTYPE>
      <TENCM>Khám phá (V6)</TENCM>
      <NGUOISX>
      </NGUOISX>
      <DTNGUOISX>
      </DTNGUOISX>
      <GHICHU>
      </GHICHU>
      <PRODUCTION_NOTE>
      </PRODUCTION_NOTE>
      <Editor_Name>
      </Editor_Name>
      <TRANGTHAI>1</TRANGTHAI>
      <NGUOITH>
      </NGUOITH>
      <NGAYTH>
      </NGAYTH>
      <HTPS>1</HTPS>
      <LUU>
      </LUU>
      <KIEU>0</KIEU>
      <CRAWL_DESC>[Aspect Conversion] Code=4 [MediaSet]</CRAWL_DESC>
      <NOTES>
      </NOTES>
      <DOHOA>
      </DOHOA>
      <MADVSX>59</MADVSX>
      <TENDVSX>
      </TENDVSX>
      <KENHPS>VTV6</KENHPS>
      <KENHPSHT>VTV6</KENHPSHT>
      <DUYET>1</DUYET>
      <LUUTULIEU>true</LUUTULIEU>
      <NGUONTULIEU>0</NGUONTULIEU>
      <QC>True</QC>
      <SOLANQC>0</SOLANQC>
      <TenCongBo>
      </TenCongBo>
      <TenChuyenMucCongbo>Khám phá</TenChuyenMucCongbo>
    </row>
    <row>
      <EXTERSTRID>T0_bb69ba3b-01b1-47fb-97b0-1a8f1f7d29b4</EXTERSTRID>
      <DURATION>180000</DURATION>
      <COD_PROGRA>SXTTTHTT_QTU21THAI_U21GANGWON</COD_PROGRA>
      <SERIES_ID>
      </SERIES_ID>
      <SERIES_NAME>
      </SERIES_NAME>
      <EPISODE>
      </EPISODE>
      <SEASON>
      </SEASON>
      <DESCRIZIO>Truyền hình trực tiếp V6: U21 Quốc tế Báo Thanh niên: U21 Thái Lan - U21 Gangwon</DESCRIZIO>
      <TITLE>Truyền hình trực tiếp V6: U21 Quốc tế Báo Thanh niên: U21 Thái Lan - U21 Gangwon</TITLE>
      <ASPECT>H</ASPECT>
      <TIMECODE_I>0</TIMECODE_I>
      <TIMECODE_O>179999</TIMECODE_O>
      <DATA>18/12/2016</DATA>
      <DATA_SCAD>16/06/2017</DATA_SCAD>
      <ORA>1395000</ORA>
      <NEWTYPE>THTT</NEWTYPE>
      <TENCM>Truyền hình trực tiếp V6</TENCM>
      <NGUOISX>
      </NGUOISX>
      <DTNGUOISX>
      </DTNGUOISX>
      <GHICHU>
      </GHICHU>
      <PRODUCTION_NOTE>
      </PRODUCTION_NOTE>
      <Editor_Name>
      </Editor_Name>
      <TRANGTHAI>1</TRANGTHAI>
      <NGUOITH>
      </NGUOITH>
      <NGAYTH>
      </NGAYTH>
      <HTPS>0</HTPS>
      <LUU>
      </LUU>
      <KIEU>0</KIEU>
      <CRAWL_DESC>[Aspect Conversion] Code=4 [MediaSet]</CRAWL_DESC>
      <NOTES>
      </NOTES>
      <DOHOA>
      </DOHOA>
      <MADVSX>129</MADVSX>
      <TENDVSX>
      </TENDVSX>
      <KENHPS>VTV6</KENHPS>
      <KENHPSHT>VTV6</KENHPSHT>
      <DUYET>1</DUYET>
      <LUUTULIEU>true</LUUTULIEU>
      <NGUONTULIEU>0</NGUONTULIEU>
      <QC>True</QC>
      <SOLANQC>0</SOLANQC>
      <TenCongBo>U21 Quốc tế Báo Thanh niên: U21 Thái Lan - U21 Gangwon</TenCongBo>
      <TenChuyenMucCongbo>Truyền hình trực tiếp</TenChuyenMucCongbo>
    </row>
    <row>
      <EXTERSTRID>T0_18600741-e37c-4d02-935f-b8a15ccb0cbf</EXTERSTRID>
      <DURATION>15000</DURATION>
      <COD_PROGRA>TKBTVKT2_GIAIDIEUTUHAOTHANG12</COD_PROGRA>
      <SERIES_ID>
      </SERIES_ID>
      <SERIES_NAME>
      </SERIES_NAME>
      <EPISODE>
      </EPISODE>
      <SEASON>
      </SEASON>
      <DESCRIZIO>VTV kết nối: Giai điệu tự hào tháng 12 (HH2312)</DESCRIZIO>
      <TITLE>VTV kết nối: Giai điệu tự hào tháng 12 (HH2312)</TITLE>
      <ASPECT>H</ASPECT>
      <TIMECODE_I>0</TIMECODE_I>
      <TIMECODE_O>14999</TIMECODE_O>
      <DATA>18/12/2016</DATA>
      <DATA_SCAD>16/02/2017</DATA_SCAD>
      <ORA>1575000</ORA>
      <NEWTYPE>VKN</NEWTYPE>
      <TENCM>VTV kết nối</TENCM>
      <NGUOISX>
      </NGUOISX>
      <DTNGUOISX>
      </DTNGUOISX>
      <GHICHU>
      </GHICHU>
      <PRODUCTION_NOTE>
      </PRODUCTION_NOTE>
      <Editor_Name>
      </Editor_Name>
      <TRANGTHAI>1</TRANGTHAI>
      <NGUOITH>
      </NGUOITH>
      <NGAYTH>
      </NGAYTH>
      <HTPS>1</HTPS>
      <LUU>
      </LUU>
      <KIEU>0</KIEU>
      <CRAWL_DESC>[Aspect Conversion] Code=4 [MediaSet]</CRAWL_DESC>
      <NOTES>
      </NOTES>
      <DOHOA>
      </DOHOA>
      <MADVSX>60</MADVSX>
      <TENDVSX>
      </TENDVSX>
      <KENHPS>VTV6</KENHPS>
      <KENHPSHT>VTV6</KENHPSHT>
      <DUYET>1</DUYET>
      <LUUTULIEU>true</LUUTULIEU>
      <NGUONTULIEU>0</NGUONTULIEU>
      <QC>True</QC>
      <SOLANQC>0</SOLANQC>
      <TenCongBo>
      </TenCongBo>
      <TenChuyenMucCongbo>VTV kết nối</TenChuyenMucCongbo>
    </row>
    <row>
      <EXTERSTRID>T0_ad9de6dc-87cb-459b-9c7c-9a4588f826a7</EXTERSTRID>
      <DURATION>195000</DURATION>
      <COD_PROGRA>SXTTTHTT_U21QTU21TNVN_MYANMAR</COD_PROGRA>
      <SERIES_ID>
      </SERIES_ID>
      <SERIES_NAME>
      </SERIES_NAME>
      <EPISODE>
      </EPISODE>
      <SEASON>
      </SEASON>
      <DESCRIZIO>Truyền hình trực tiếp V6: U21 Quốc tế Báo Thanh niên: Lễ khai mac &amp; trận Khai mạc U21 Báo TNVN - U21 Myanmar</DESCRIZIO>
      <TITLE>Truyền hình trực tiếp V6: U21 Quốc tế Báo Thanh niên: Lễ khai mac &amp; trận Khai mạc U21 Báo TNVN - U21 Myanmar</TITLE>
      <ASPECT>H</ASPECT>
      <TIMECODE_I>0</TIMECODE_I>
      <TIMECODE_O>194999</TIMECODE_O>
      <DATA>18/12/2016</DATA>
      <DATA_SCAD>16/06/2017</DATA_SCAD>
      <ORA>1597500</ORA>
      <NEWTYPE>THTT</NEWTYPE>
      <TENCM>Truyền hình trực tiếp V6</TENCM>
      <NGUOISX>
      </NGUOISX>
      <DTNGUOISX>
      </DTNGUOISX>
      <GHICHU>
      </GHICHU>
      <PRODUCTION_NOTE>
      </PRODUCTION_NOTE>
      <Editor_Name>
      </Editor_Name>
      <TRANGTHAI>1</TRANGTHAI>
      <NGUOITH>
      </NGUOITH>
      <NGAYTH>
      </NGAYTH>
      <HTPS>0</HTPS>
      <LUU>
      </LUU>
      <KIEU>0</KIEU>
      <CRAWL_DESC>[Aspect Conversion] Code=4 [MediaSet]</CRAWL_DESC>
      <NOTES>
      </NOTES>
      <DOHOA>
      </DOHOA>
      <MADVSX>129</MADVSX>
      <TENDVSX>
      </TENDVSX>
      <KENHPS>VTV6</KENHPS>
      <KENHPSHT>VTV6</KENHPSHT>
      <DUYET>1</DUYET>
      <LUUTULIEU>true</LUUTULIEU>
      <NGUONTULIEU>0</NGUONTULIEU>
      <QC>True</QC>
      <SOLANQC>0</SOLANQC>
      <TenCongBo>U21 Quốc tế Báo Thanh niên: Lễ khai mac &amp; trận Khai mạc U21 Báo TNVN - U21 Myanmar</TenCongBo>
      <TenChuyenMucCongbo>Truyền hình trực tiếp</TenChuyenMucCongbo>
    </row>
    <row>
      <EXTERSTRID>N1_202376</EXTERSTRID>
      <DURATION>1500</DURATION>
      <COD_PROGRA>DH.V6.HOMNAY.18H-24H</COD_PROGRA>
      <SERIES_ID>
      </SERIES_ID>
      <SERIES_NAME>
      </SERIES_NAME>
      <EPISODE>
      </EPISODE>
      <SEASON>
      </SEASON>
      <DESCRIZIO>Trôi - Hôm nay - 18h00 - 24h00 (Ngày HH: 31/12/2016)</DESCRIZIO>
      <TITLE>Trôi - Hôm nay - 18h00 - 24h00 (Ngày HH: 31/12/2016)</TITLE>
      <ASPECT>H</ASPECT>
      <TIMECODE_I>0</TIMECODE_I>
      <TIMECODE_O>1499</TIMECODE_O>
      <DATA>18/12/2016</DATA>
      <ORA>1708500</ORA>
      <NEWTYPE>CDQB</NEWTYPE>
      <TENCM>Nhận diện kênh</TENCM>
      <MADVSX>
      </MADVSX>
      <TENDVSX>
      </TENDVSX>
      <NGUOISX>
      </NGUOISX>
      <DTNGUOISX>
      </DTNGUOISX>
      <GHICHU>
      </GHICHU>
      <PRODUCTION_NOTE>
      </PRODUCTION_NOTE>
      <Editor_Name>
      </Editor_Name>
      <TRANGTHAI>1</TRANGTHAI>
      <NGUOITH>
      </NGUOITH>
      <NGAYTH>
      </NGAYTH>
      <HTPS>0</HTPS>
      <LUU>
      </LUU>
      <KIEU>1</KIEU>
      <DOHOA>
      </DOHOA>
      <KENHPS>VTV6</KENHPS>
      <DUYET>1</DUYET>
      <LUUTULIEU>True</LUUTULIEU>
      <NGUONTULIEU>True</NGUONTULIEU>
      <QC>True</QC>
      <DATA_SCAD>07/01/2017</DATA_SCAD>
      <SOLANQC>0</SOLANQC>
      <TenCongBo>
      </TenCongBo>
      <TenChuyenMucCongbo>
      </TenChuyenMucCongbo>
    </row>
    <row>
      <EXTERSTRID>T01_2c9d35bd-bad0-44b1-9c89-2c77a841822c</EXTERSTRID>
      <DURATION>750</DURATION>
      <COD_PROGRA>BHDBDPC_SO54_2016</COD_PROGRA>
      <SERIES_ID>
      </SERIES_ID>
      <SERIES_NAME>
      </SERIES_NAME>
      <EPISODE>
      </EPISODE>
      <SEASON>
      </SEASON>
      <DESCRIZIO>Biệt đội phong cách: Số 54 - 2016 (2 lần Pop up, 4 lần Logo xoay - Không chạy khi phát lại)_1</DESCRIZIO>
      <TITLE>Biệt đội phong cách: Số 54 - 2016 (2 lần Pop up, 4 lần Logo xoay - Không chạy khi phát lại)_1</TITLE>
      <ASPECT>H</ASPECT>
      <TIMECODE_I>0</TIMECODE_I>
      <TIMECODE_O>18749</TIMECODE_O>
      <DATA>18/12/2016</DATA>
      <DATA_SCAD>18/12/2017</DATA_SCAD>
      <ORA>1792500</ORA>
      <NEWTYPE>BDPC</NEWTYPE>
      <TENCM>Biệt đội phong cách</TENCM>
      <NGUOISX>
      </NGUOISX>
      <DTNGUOISX>
      </DTNGUOISX>
      <GHICHU>
      </GHICHU>
      <PRODUCTION_NOTE>
      </PRODUCTION_NOTE>
      <Editor_Name>
      </Editor_Name>
      <TRANGTHAI>1</TRANGTHAI>
      <NGUOITH>
      </NGUOITH>
      <NGAYTH>
      </NGAYTH>
      <HTPS>0</HTPS>
      <LUU>
      </LUU>
      <KIEU>0</KIEU>
      <CRAWL_DESC>[Aspect Conversion] Code=4 [MediaSet]</CRAWL_DESC>
      <NOTES>
      </NOTES>
      <DOHOA>
      </DOHOA>
      <MADVSX>
      </MADVSX>
      <TENDVSX>
      </TENDVSX>
      <KENHPS>VTV6</KENHPS>
      <KENHPSHT>VTV6</KENHPSHT>
      <DUYET>0</DUYET>
      <LUUTULIEU>true</LUUTULIEU>
      <NGUONTULIEU>0</NGUONTULIEU>
      <QC>True</QC>
      <SOLANQC>0</SOLANQC>
      <TenCongBo>
      </TenCongBo>
      <TenChuyenMucCongbo>Biệt đội phong cách</TenChuyenMucCongbo>
    </row>
    <row>
      <EXTERSTRID>T02_2c9d35bd-bad0-44b1-9c89-2c77a841822c</EXTERSTRID>
      <DURATION>750</DURATION>
      <COD_PROGRA>BHDBDPC_SO54_2016_2</COD_PROGRA>
      <SERIES_ID>
      </SERIES_ID>
      <SERIES_NAME>
      </SERIES_NAME>
      <EPISODE>
      </EPISODE>
      <SEASON>
      </SEASON>
      <DESCRIZIO>Biệt đội phong cách: Số 54 - 2016 (2 lần Pop up, 4 lần Logo xoay - Không chạy khi phát lại)_2</DESCRIZIO>
      <TITLE>Biệt đội phong cách: Số 54 - 2016 (2 lần Pop up, 4 lần Logo xoay - Không chạy khi phát lại)_2</TITLE>
      <ASPECT>H</ASPECT>
      <TIMECODE_I>0</TIMECODE_I>
      <TIMECODE_O>18749</TIMECODE_O>
      <DATA>18/12/2016</DATA>
      <DATA_SCAD>18/12/2017</DATA_SCAD>
      <ORA>1793250</ORA>
      <NEWTYPE>BDPC</NEWTYPE>
      <TENCM>Biệt đội phong cách</TENCM>
      <NGUOISX>
      </NGUOISX>
      <DTNGUOISX>
      </DTNGUOISX>
      <GHICHU>
      </GHICHU>
      <PRODUCTION_NOTE>
      </PRODUCTION_NOTE>
      <Editor_Name>
      </Editor_Name>
      <TRANGTHAI>1</TRANGTHAI>
      <NGUOITH>
      </NGUOITH>
      <NGAYTH>
      </NGAYTH>
      <HTPS>0</HTPS>
      <LUU>
      </LUU>
      <KIEU>0</KIEU>
      <CRAWL_DESC>[Aspect Conversion] Code=4 [MediaSet]</CRAWL_DESC>
      <NOTES>
      </NOTES>
      <DOHOA>
      </DOHOA>
      <MADVSX>
      </MADVSX>
      <TENDVSX>
      </TENDVSX>
      <KENHPS>VTV6</KENHPS>
      <KENHPSHT>VTV6</KENHPSHT>
      <DUYET>0</DUYET>
      <LUUTULIEU>true</LUUTULIEU>
      <NGUONTULIEU>0</NGUONTULIEU>
      <QC>True</QC>
      <SOLANQC>0</SOLANQC>
      <TenCongBo>
      </TenCongBo>
      <TenChuyenMucCongbo>Biệt đội phong cách</TenChuyenMucCongbo>
    </row>
    <row>
      <EXTERSTRID>T03_2c9d35bd-bad0-44b1-9c89-2c77a841822c</EXTERSTRID>
      <DURATION>750</DURATION>
      <COD_PROGRA>BHDBDPC_SO54_2016_3</COD_PROGRA>
      <SERIES_ID>
      </SERIES_ID>
      <SERIES_NAME>
      </SERIES_NAME>
      <EPISODE>
      </EPISODE>
      <SEASON>
      </SEASON>
      <DESCRIZIO>Biệt đội phong cách: Số 54 - 2016 (2 lần Pop up, 4 lần Logo xoay - Không chạy khi phát lại)_3</DESCRIZIO>
      <TITLE>Biệt đội phong cách: Số 54 - 2016 (2 lần Pop up, 4 lần Logo xoay - Không chạy khi phát lại)_3</TITLE>
      <ASPECT>H</ASPECT>
      <TIMECODE_I>0</TIMECODE_I>
      <TIMECODE_O>18749</TIMECODE_O>
      <DATA>18/12/2016</DATA>
      <DATA_SCAD>18/12/2017</DATA_SCAD>
      <ORA>1794000</ORA>
      <NEWTYPE>BDPC</NEWTYPE>
      <TENCM>Biệt đội phong cách</TENCM>
      <NGUOISX>
      </NGUOISX>
      <DTNGUOISX>
      </DTNGUOISX>
      <GHICHU>
      </GHICHU>
      <PRODUCTION_NOTE>
      </PRODUCTION_NOTE>
      <Editor_Name>
      </Editor_Name>
      <TRANGTHAI>1</TRANGTHAI>
      <NGUOITH>
      </NGUOITH>
      <NGAYTH>
      </NGAYTH>
      <HTPS>0</HTPS>
      <LUU>
      </LUU>
      <KIEU>0</KIEU>
      <CRAWL_DESC>[Aspect Conversion] Code=4 [MediaSet]</CRAWL_DESC>
      <NOTES>
      </NOTES>
      <DOHOA>
      </DOHOA>
      <MADVSX>
      </MADVSX>
      <TENDVSX>
      </TENDVSX>
      <KENHPS>VTV6</KENHPS>
      <KENHPSHT>VTV6</KENHPSHT>
      <DUYET>0</DUYET>
      <LUUTULIEU>true</LUUTULIEU>
      <NGUONTULIEU>0</NGUONTULIEU>
      <QC>True</QC>
      <SOLANQC>0</SOLANQC>
      <TenCongBo>
      </TenCongBo>
      <TenChuyenMucCongbo>Biệt đội phong cách</TenChuyenMucCongbo>
    </row>
    <row>
      <EXTERSTRID>T04_2c9d35bd-bad0-44b1-9c89-2c77a841822c</EXTERSTRID>
      <DURATION>750</DURATION>
      <COD_PROGRA>BHDBDPC_SO54_2016_4</COD_PROGRA>
      <SERIES_ID>
      </SERIES_ID>
      <SERIES_NAME>
      </SERIES_NAME>
      <EPISODE>
      </EPISODE>
      <SEASON>
      </SEASON>
      <DESCRIZIO>Biệt đội phong cách: Số 54 - 2016 (2 lần Pop up, 4 lần Logo xoay - Không chạy khi phát lại)_4</DESCRIZIO>
      <TITLE>Biệt đội phong cách: Số 54 - 2016 (2 lần Pop up, 4 lần Logo xoay - Không chạy khi phát lại)_4</TITLE>
      <ASPECT>H</ASPECT>
      <TIMECODE_I>0</TIMECODE_I>
      <TIMECODE_O>18749</TIMECODE_O>
      <DATA>18/12/2016</DATA>
      <DATA_SCAD>18/12/2017</DATA_SCAD>
      <ORA>1794750</ORA>
      <NEWTYPE>BDPC</NEWTYPE>
      <TENCM>Biệt đội phong cách</TENCM>
      <NGUOISX>
      </NGUOISX>
      <DTNGUOISX>
      </DTNGUOISX>
      <GHICHU>
      </GHICHU>
      <PRODUCTION_NOTE>
      </PRODUCTION_NOTE>
      <Editor_Name>
      </Editor_Name>
      <TRANGTHAI>1</TRANGTHAI>
      <NGUOITH>
      </NGUOITH>
      <NGAYTH>
      </NGAYTH>
      <HTPS>0</HTPS>
      <LUU>
      </LUU>
      <KIEU>0</KIEU>
      <CRAWL_DESC>[Aspect Conversion] Code=4 [MediaSet]</CRAWL_DESC>
      <NOTES>
      </NOTES>
      <DOHOA>
      </DOHOA>
      <MADVSX>
      </MADVSX>
      <TENDVSX>
      </TENDVSX>
      <KENHPS>VTV6</KENHPS>
      <KENHPSHT>VTV6</KENHPSHT>
      <DUYET>0</DUYET>
      <LUUTULIEU>true</LUUTULIEU>
      <NGUONTULIEU>0</NGUONTULIEU>
      <QC>True</QC>
      <SOLANQC>0</SOLANQC>
      <TenCongBo>
      </TenCongBo>
      <TenChuyenMucCongbo>Biệt đội phong cách</TenChuyenMucCongbo>
    </row>
    <row>
      <EXTERSTRID>T0_60d51926-57f5-4d7b-98ab-82eda640f75c</EXTERSTRID>
      <DURATION>67500</DURATION>
      <COD_PROGRA>TTNSTKN_SO402016</COD_PROGRA>
      <SERIES_ID>
      </SERIES_ID>
      <SERIES_NAME>
      </SERIES_NAME>
      <EPISODE>
      </EPISODE>
      <SEASON>
      </SEASON>
      <DESCRIZIO>Sáng tạo khởi nghiệp (V6): Số 40/2016</DESCRIZIO>
      <TITLE>Sáng tạo khởi nghiệp (V6): Số 40/2016</TITLE>
      <ASPECT>H</ASPECT>
      <TIMECODE_I>0</TIMECODE_I>
      <TIMECODE_O>67499</TIMECODE_O>
      <DATA>18/12/2016</DATA>
      <DATA_SCAD>18/12/2017</DATA_SCAD>
      <ORA>1890000</ORA>
      <NEWTYPE>STKN</NEWTYPE>
      <TENCM>Sáng tạo khởi nghiệp (V6)</TENCM>
      <NGUOISX>
      </NGUOISX>
      <DTNGUOISX>
      </DTNGUOISX>
      <GHICHU>
      </GHICHU>
      <PRODUCTION_NOTE>
      </PRODUCTION_NOTE>
      <Editor_Name>
      </Editor_Name>
      <TRANGTHAI>1</TRANGTHAI>
      <NGUOITH>
      </NGUOITH>
      <NGAYTH>
      </NGAYTH>
      <HTPS>0</HTPS>
      <LUU>
      </LUU>
      <KIEU>0</KIEU>
      <CRAWL_DESC>[Aspect Conversion] Code=4 [MediaSet]</CRAWL_DESC>
      <NOTES>
      </NOTES>
      <DOHOA>
      </DOHOA>
      <MADVSX>87</MADVSX>
      <TENDVSX>
      </TENDVSX>
      <KENHPS>VTV6</KENHPS>
      <KENHPSHT>VTV6</KENHPSHT>
      <DUYET>1</DUYET>
      <LUUTULIEU>true</LUUTULIEU>
      <NGUONTULIEU>0</NGUONTULIEU>
      <QC>True</QC>
      <SOLANQC>0</SOLANQC>
      <TenCongBo>
      </TenCongBo>
      <TenChuyenMucCongbo>Sáng tạo khởi nghiệp</TenChuyenMucCongbo>
    </row>
    <row>
      <EXTERSTRID>T0_03369b4b-2c67-4215-8e42-4e2b238e45ca</EXTERSTRID>
      <DURATION>15000</DURATION>
      <COD_PROGRA>TKBTVKT2_GIAIDIEUTUHAOTHANG12</COD_PROGRA>
      <SERIES_ID>
      </SERIES_ID>
      <SERIES_NAME>
      </SERIES_NAME>
      <EPISODE>
      </EPISODE>
      <SEASON>
      </SEASON>
      <DESCRIZIO>VTV kết nối: Giai điệu tự hào tháng 12 (HH2312)</DESCRIZIO>
      <TITLE>VTV kết nối: Giai điệu tự hào tháng 12 (HH2312)</TITLE>
      <ASPECT>H</ASPECT>
      <TIMECODE_I>0</TIMECODE_I>
      <TIMECODE_O>14999</TIMECODE_O>
      <DATA>18/12/2016</DATA>
      <DATA_SCAD>16/02/2017</DATA_SCAD>
      <ORA>1957500</ORA>
      <NEWTYPE>VKN</NEWTYPE>
      <TENCM>VTV kết nối</TENCM>
      <NGUOISX>
      </NGUOISX>
      <DTNGUOISX>
      </DTNGUOISX>
      <GHICHU>
      </GHICHU>
      <PRODUCTION_NOTE>
      </PRODUCTION_NOTE>
      <Editor_Name>
      </Editor_Name>
      <TRANGTHAI>1</TRANGTHAI>
      <NGUOITH>
      </NGUOITH>
      <NGAYTH>
      </NGAYTH>
      <HTPS>1</HTPS>
      <LUU>
      </LUU>
      <KIEU>0</KIEU>
      <CRAWL_DESC>[Aspect Conversion] Code=4 [MediaSet]</CRAWL_DESC>
      <NOTES>
      </NOTES>
      <DOHOA>
      </DOHOA>
      <MADVSX>60</MADVSX>
      <TENDVSX>
      </TENDVSX>
      <KENHPS>VTV6</KENHPS>
      <KENHPSHT>VTV6</KENHPSHT>
      <DUYET>1</DUYET>
      <LUUTULIEU>true</LUUTULIEU>
      <NGUONTULIEU>0</NGUONTULIEU>
      <QC>True</QC>
      <SOLANQC>0</SOLANQC>
      <TenCongBo>
      </TenCongBo>
      <TenChuyenMucCongbo>VTV kết nối</TenChuyenMucCongbo>
    </row>
    <row>
      <EXTERSTRID>T0_03709b7e-d8e3-4876-9ee9-7171c4d0bb22</EXTERSTRID>
      <DURATION>1500</DURATION>
      <COD_PROGRA>22H0_VTV6_18122016_2155</COD_PROGRA>
      <SERIES_ID>
      </SERIES_ID>
      <SERIES_NAME>
      </SERIES_NAME>
      <EPISODE>
      </EPISODE>
      <SEASON>
      </SEASON>
      <DESCRIZIO>Thời tiết V6 22h00: Thời tiết V6 22h00</DESCRIZIO>
      <TITLE>Thời tiết V6 22h00: Thời tiết V6 22h00</TITLE>
      <ASPECT>H</ASPECT>
      <TIMECODE_I>0</TIMECODE_I>
      <TIMECODE_O>1499</TIMECODE_O>
      <DATA>18/12/2016</DATA>
      <DATA_SCAD>22/12/2016</DATA_SCAD>
      <ORA>1972500</ORA>
      <NEWTYPE>22H0</NEWTYPE>
      <TENCM>Thời tiết V6 22h00</TENCM>
      <NGUOISX>
      </NGUOISX>
      <DTNGUOISX>
      </DTNGUOISX>
      <GHICHU>
      </GHICHU>
      <PRODUCTION_NOTE>
      </PRODUCTION_NOTE>
      <Editor_Name>
      </Editor_Name>
      <TRANGTHAI>1</TRANGTHAI>
      <NGUOITH>
      </NGUOITH>
      <NGAYTH>
      </NGAYTH>
      <HTPS>0</HTPS>
      <LUU>
      </LUU>
      <KIEU>5</KIEU>
      <CRAWL_DESC>[Aspect Conversion] Code=4 [MediaSet]</CRAWL_DESC>
      <NOTES>
      </NOTES>
      <DOHOA>
      </DOHOA>
      <MADVSX>0</MADVSX>
      <TENDVSX>
      </TENDVSX>
      <KENHPS>VTV6</KENHPS>
      <KENHPSHT>VTV6</KENHPSHT>
      <DUYET>0</DUYET>
      <LUUTULIEU>true</LUUTULIEU>
      <NGUONTULIEU>0</NGUONTULIEU>
      <QC>True</QC>
      <SOLANQC>0</SOLANQC>
      <TenCongBo>
      </TenCongBo>
      <TenChuyenMucCongbo>Thời tiết</TenChuyenMucCongbo>
    </row>
    <row>
      <EXTERSTRID>N1_202776</EXTERSTRID>
      <DURATION>1500</DURATION>
      <COD_PROGRA>DH.V6.NGAYMAI.00H-24H</COD_PROGRA>
      <SERIES_ID>
      </SERIES_ID>
      <SERIES_NAME>
      </SERIES_NAME>
      <EPISODE>
      </EPISODE>
      <SEASON>
      </SEASON>
      <DESCRIZIO>Trôi ngày mai - 22h00 (Ngày HH: 31/12/2016)</DESCRIZIO>
      <TITLE>Trôi ngày mai - 22h00 (Ngày HH: 31/12/2016)</TITLE>
      <ASPECT>H</ASPECT>
      <TIMECODE_I>0</TIMECODE_I>
      <TIMECODE_O>1499</TIMECODE_O>
      <DATA>18/12/2016</DATA>
      <ORA>1978500</ORA>
      <NEWTYPE>CDQB</NEWTYPE>
      <TENCM>Nhận diện kênh</TENCM>
      <MADVSX>
      </MADVSX>
      <TENDVSX>
      </TENDVSX>
      <NGUOISX>
      </NGUOISX>
      <DTNGUOISX>
      </DTNGUOISX>
      <GHICHU>
      </GHICHU>
      <PRODUCTION_NOTE>
      </PRODUCTION_NOTE>
      <Editor_Name>
      </Editor_Name>
      <TRANGTHAI>1</TRANGTHAI>
      <NGUOITH>
      </NGUOITH>
      <NGAYTH>
      </NGAYTH>
      <HTPS>0</HTPS>
      <LUU>
      </LUU>
      <KIEU>1</KIEU>
      <DOHOA>
      </DOHOA>
      <KENHPS>VTV6</KENHPS>
      <DUYET>1</DUYET>
      <LUUTULIEU>True</LUUTULIEU>
      <NGUONTULIEU>True</NGUONTULIEU>
      <QC>True</QC>
      <DATA_SCAD>07/01/2017</DATA_SCAD>
      <SOLANQC>0</SOLANQC>
      <TenCongBo>
      </TenCongBo>
      <TenChuyenMucCongbo>
      </TenChuyenMucCongbo>
    </row>
    <row>
      <EXTERSTRID>T0_7fb80f3b-807b-43f0-82ee-dd04ded7b980</EXTERSTRID>
      <DURATION>45000</DURATION>
      <COD_PROGRA>360T_VTV6_18122016_2200</COD_PROGRA>
      <SERIES_ID>
      </SERIES_ID>
      <SERIES_NAME>
      </SERIES_NAME>
      <EPISODE>
      </EPISODE>
      <SEASON>
      </SEASON>
      <DESCRIZIO>360° Thể thao: 360° Thể thao</DESCRIZIO>
      <TITLE>360° Thể thao: 360° Thể thao</TITLE>
      <ASPECT>H</ASPECT>
      <TIMECODE_I>0</TIMECODE_I>
      <TIMECODE_O>44999</TIMECODE_O>
      <DATA>18/12/2016</DATA>
      <DATA_SCAD>16/06/2017</DATA_SCAD>
      <ORA>1980000</ORA>
      <NEWTYPE>360T</NEWTYPE>
      <TENCM>360° Thể thao</TENCM>
      <NGUOISX>
      </NGUOISX>
      <DTNGUOISX>
      </DTNGUOISX>
      <GHICHU>
      </GHICHU>
      <PRODUCTION_NOTE>
      </PRODUCTION_NOTE>
      <Editor_Name>
      </Editor_Name>
      <TRANGTHAI>1</TRANGTHAI>
      <NGUOITH>
      </NGUOITH>
      <NGAYTH>
      </NGAYTH>
      <HTPS>0</HTPS>
      <LUU>
      </LUU>
      <KIEU>0</KIEU>
      <CRAWL_DESC>[Aspect Conversion] Code=4 [MediaSet]</CRAWL_DESC>
      <NOTES>
      </NOTES>
      <DOHOA>
      </DOHOA>
      <MADVSX>0</MADVSX>
      <TENDVSX>
      </TENDVSX>
      <KENHPS>VTV6</KENHPS>
      <KENHPSHT>VTV6</KENHPSHT>
      <DUYET>1</DUYET>
      <LUUTULIEU>true</LUUTULIEU>
      <NGUONTULIEU>0</NGUONTULIEU>
      <QC>True</QC>
      <SOLANQC>0</SOLANQC>
      <TenCongBo>
      </TenCongBo>
      <TenChuyenMucCongbo>360° thể thao</TenChuyenMucCongbo>
    </row>
    <row>
      <EXTERSTRID>T0_a26e23a7-a16b-41ee-a859-397fdaae701e</EXTERSTRID>
      <DURATION>80150</DURATION>
      <COD_PROGRA>TTNHNAD_SO52</COD_PROGRA>
      <SERIES_ID>
      </SERIES_ID>
      <SERIES_NAME>
      </SERIES_NAME>
      <EPISODE>
      </EPISODE>
      <SEASON>
      </SEASON>
      <DESCRIZIO>Hôm nay ai đến?: Số 52</DESCRIZIO>
      <TITLE>Hôm nay ai đến?: Số 52</TITLE>
      <ASPECT>H</ASPECT>
      <TIMECODE_I>0</TIMECODE_I>
      <TIMECODE_O>80149</TIMECODE_O>
      <DATA>18/12/2016</DATA>
      <DATA_SCAD>18/12/2017</DATA_SCAD>
      <ORA>2025000</ORA>
      <NEWTYPE>HNAD</NEWTYPE>
      <TENCM>Hôm nay ai đến?</TENCM>
      <NGUOISX>
      </NGUOISX>
      <DTNGUOISX>
      </DTNGUOISX>
      <GHICHU>
      </GHICHU>
      <PRODUCTION_NOTE>
      </PRODUCTION_NOTE>
      <Editor_Name>
      </Editor_Name>
      <TRANGTHAI>1</TRANGTHAI>
      <NGUOITH>
      </NGUOITH>
      <NGAYTH>
      </NGAYTH>
      <HTPS>1</HTPS>
      <LUU>
      </LUU>
      <KIEU>0</KIEU>
      <CRAWL_DESC>[Aspect Conversion] Code=4 [MediaSet]</CRAWL_DESC>
      <NOTES>
      </NOTES>
      <DOHOA>
      </DOHOA>
      <MADVSX>87</MADVSX>
      <TENDVSX>
      </TENDVSX>
      <KENHPS>VTV6</KENHPS>
      <KENHPSHT>VTV6</KENHPSHT>
      <DUYET>1</DUYET>
      <LUUTULIEU>true</LUUTULIEU>
      <NGUONTULIEU>0</NGUONTULIEU>
      <QC>True</QC>
      <SOLANQC>0</SOLANQC>
      <TenCongBo>
      </TenCongBo>
      <TenChuyenMucCongbo>Hôm nay ai đến?</TenChuyenMucCongbo>
    </row>
    <row>
      <EXTERSTRID>T0_30dad47c-8d99-45d4-bcf3-c6e5dc650d84</EXTERSTRID>
      <DURATION>22500</DURATION>
      <COD_PROGRA>SXTTTHAO_NHATKYAFF_18122016</COD_PROGRA>
      <SERIES_ID>
      </SERIES_ID>
      <SERIES_NAME>
      </SERIES_NAME>
      <EPISODE>
      </EPISODE>
      <SEASON>
      </SEASON>
      <DESCRIZIO>Thể thao 30: Nhật ký AFF Suzuki Cup 2016 - 18/12/2016</DESCRIZIO>
      <TITLE>Thể thao 30: Nhật ký AFF Suzuki Cup 2016 - 18/12/2016</TITLE>
      <ASPECT>H</ASPECT>
      <TIMECODE_I>0</TIMECODE_I>
      <TIMECODE_O>22499</TIMECODE_O>
      <DATA>18/12/2016</DATA>
      <DATA_SCAD>28/12/2016</DATA_SCAD>
      <ORA>2070000</ORA>
      <NEWTYPE>THAO</NEWTYPE>
      <TENCM>Thể thao 30</TENCM>
      <NGUOISX>
      </NGUOISX>
      <DTNGUOISX>
      </DTNGUOISX>
      <GHICHU>
      </GHICHU>
      <PRODUCTION_NOTE>
      </PRODUCTION_NOTE>
      <Editor_Name>
      </Editor_Name>
      <TRANGTHAI>1</TRANGTHAI>
      <NGUOITH>
      </NGUOITH>
      <NGAYTH>
      </NGAYTH>
      <HTPS>0</HTPS>
      <LUU>
      </LUU>
      <KIEU>0</KIEU>
      <CRAWL_DESC>[Aspect Conversion] Code=4 [MediaSet]</CRAWL_DESC>
      <NOTES>
      </NOTES>
      <DOHOA>
      </DOHOA>
      <MADVSX>129</MADVSX>
      <TENDVSX>
      </TENDVSX>
      <KENHPS>VTV6</KENHPS>
      <KENHPSHT>VTV6</KENHPSHT>
      <DUYET>0</DUYET>
      <LUUTULIEU>true</LUUTULIEU>
      <NGUONTULIEU>0</NGUONTULIEU>
      <QC>True</QC>
      <SOLANQC>0</SOLANQC>
      <TenCongBo>Nhật ký AFF Suzuki Cup 2016</TenCongBo>
      <TenChuyenMucCongbo>Thể thao</TenChuyenMucCongbo>
    </row>
    <row>
      <EXTERSTRID>T0_6549ad51-cd9f-4731-b07b-cd6cffde2ba2</EXTERSTRID>
      <DURATION>135000</DURATION>
      <COD_PROGRA>SXTTTT_FIFACLUB16HANGBA</COD_PROGRA>
      <SERIES_ID>
      </SERIES_ID>
      <SERIES_NAME>
      </SERIES_NAME>
      <EPISODE>
      </EPISODE>
      <SEASON>
      </SEASON>
      <DESCRIZIO>Thể thao: FIFA Club World Cup 2016: Trận tranh hạng ba (Ghi Live lúc 13h)</DESCRIZIO>
      <TITLE>Thể thao: FIFA Club World Cup 2016: Trận tranh hạng ba (Ghi Live lúc 13h)</TITLE>
      <ASPECT>H</ASPECT>
      <TIMECODE_I>0</TIMECODE_I>
      <TIMECODE_O>134999</TIMECODE_O>
      <DATA>18/12/2016</DATA>
      <DATA_SCAD>16/06/2017</DATA_SCAD>
      <ORA>2092500</ORA>
      <NEWTYPE>TT</NEWTYPE>
      <TENCM>Thể thao</TENCM>
      <NGUOISX>
      </NGUOISX>
      <DTNGUOISX>
      </DTNGUOISX>
      <GHICHU>
      </GHICHU>
      <PRODUCTION_NOTE>
      </PRODUCTION_NOTE>
      <Editor_Name>
      </Editor_Name>
      <TRANGTHAI>1</TRANGTHAI>
      <NGUOITH>
      </NGUOITH>
      <NGAYTH>
      </NGAYTH>
      <HTPS>0</HTPS>
      <LUU>
      </LUU>
      <KIEU>0</KIEU>
      <CRAWL_DESC>[Aspect Conversion] Code=4 [MediaSet]</CRAWL_DESC>
      <NOTES>
      </NOTES>
      <DOHOA>
      </DOHOA>
      <MADVSX>129</MADVSX>
      <TENDVSX>
      </TENDVSX>
      <KENHPS>VTV6</KENHPS>
      <KENHPSHT>VTV6</KENHPSHT>
      <DUYET>0</DUYET>
      <LUUTULIEU>true</LUUTULIEU>
      <NGUONTULIEU>0</NGUONTULIEU>
      <QC>True</QC>
      <SOLANQC>0</SOLANQC>
      <TenCongBo>FIFA Club World Cup 2016: Trận tranh hạng ba</TenCongBo>
      <TenChuyenMucCongbo>Thể thao</TenChuyenMucCongbo>
    </row>
  </TRAFFICXML>
</data>